{"rn1qkb1r/pb1p1ppp/1p2pn2/2p5/2PP4/5NP1/PP2PPBP/RNBQ1RK1 b kq -":{"w":7,"d":6,"b":6,"r":2611,"m":[{"san":"cxd4","uci":"c5d4","w":7,"d":5,"b":6,"r":2611},{"san":"Be7","uci":"f8e7","w":0,"d":1,"b":0,"r":2600}],"g":["mc80420","mc85390","mc13920","mc89121","mc74600","mc13176","mc49000","mc49008","mc450","mc48509"]},"r1bqkb1r/pp1npppp/2p2n2/6N1/3P4/3B4/PPP2PPP/R1BQK1NR b KQkq -":{"w":41,"d":61,"b":18,"r":2688,"m":[{"san":"e6","uci":"e7e6","w":36,"d":58,"b":16,"r":2693},{"san":"g6","uci":"g7g6","w":1,"d":1,"b":1,"r":2678},{"san":"Nb6","uci":"d7b6","w":2,"d":0,"b":0,"r":2580},{"san":"e5","uci":"e7e5","w":1,"d":1,"b":0,"r":2722},{"san":"Qc7","uci":"d8c7","w":0,"d":1,"b":1,"r":2563},{"san":"c5","uci":"c6c5","w":1,"d":0,"b":0,"r":2530}],"g":["mc52491","mc5914","mc67345","mc49845","mc49872","mc5922","mc50060","mc49849","mc43988","mc45303"]},"r1bqk2r/pppp1ppp/2n2n2/2b1p3/2B1P3/2PP1N2/PP3PPP/RNBQK2R b KQkq -":{"w":235,"d":474,"b":241,"r":2721,"m":[{"san":"d6","uci":"d7d6","w":149,"d":266,"b":145,"r":2727},{"san":"O-O","uci":"e8g8","w":45,"d":110,"b":45,"r":2727},{"san":"a6","uci":"a7a6","w":36,"d":85,"b":40,"r":2690},{"san":"h6","uci":"h7h6","w":4,"d":10,"b":9,"r":2757},{"san":"a5","uci":"a7a5","w":1,"d":3,"b":2,"r":2691}],"g":["mc26375","mc20091","mc19219","mc61618","mc84423","mc21149","mc21279","mc84318","mc21080","mc20311"]},"r1bqk2r/pppnbppp/3p1n2/4p3/2BPP3/2N2N2/PPP2PPP/R1BQ1RK1 b kq -":{"w":76,"d":37,"b":10,"r":2669,"m":[{"san":"O-O","uci":"e8g8","w":67,"d":35,"b":10,"r":2666},{"san":"c6","uci":"c7c6","w":4,"d":2,"b":0,"r":2678},{"san":"exd4","uci":"e5d4","w":4,"d":0,"b":0,"r":2760},{"san":"Nb6","uci":"d7b6","w":1,"d":0,"b":0,"r":2583}],"g":["mc25005","mc18731","mc18612","mc24031","mc29265","mc24954","mc10454","mc23857","mc23171","mc18052"]},"r1bqkb1r/pp3ppp/2pp1n2/4p3/B3P3/2NP1Q2/PPP2PPP/R1B2RK1 b kq -":{"w":1,"d":2,"b":0,"r":2597,"m":[{"san":"Be7","uci":"f8e7","w":1,"d":1,"b":0,"r":2651},{"san":"Bg4","uci":"c8g4","w":0,"d":1,"b":0,"r":2490}],"g":["mc5760","mc365","mc101570"]},"r2qkb1r/1ppb1ppp/p1np2n1/3Pp3/B3P3/2P2N2/PP3PPP/RNBQ1RK1 b kq -":{"w":1,"d":7,"b":1,"r":2645,"m":[{"san":"Nb8","uci":"c6b8","w":1,"d":7,"b":1,"r":2645}],"g":["mc45810","mc67478","mc12730","mc5456","mc92257","mc81833","mc477","mc53927","mc54555"]},"rnbqkb1r/pp2pppp/1n1p4/3P4/2P5/8/PP3PPP/RNBQKBNR b KQkq -":{"w":1,"d":2,"b":1,"r":2599,"m":[{"san":"e5","uci":"e7e5","w":0,"d":1,"b":1,"r":2604},{"san":"N8d7","uci":"b8d7","w":0,"d":1,"b":0,"r":2535},{"san":"e6","uci":"e7e6","w":1,"d":0,"b":0,"r":2652}],"g":["mc94456","mc94053","mc601","mc73517"]},"r1b1kbnr/pp2pppp/2n5/2pq4/3P4/2P2N2/PP3PPP/RNBQKB1R b KQkq -":{"w":8,"d":6,"b":9,"r":2633,"m":[{"san":"Nf6","uci":"g8f6","w":4,"d":2,"b":2,"r":2661},{"san":"Bg4","uci":"c8g4","w":2,"d":2,"b":1,"r":2580},{"san":"e6","uci":"e7e6","w":0,"d":0,"b":3,"r":2582},{"san":"cxd4","uci":"c5d4","w":2,"d":0,"b":1,"r":2642},{"san":"e5","uci":"e7e5","w":0,"d":2,"b":0,"r":2639},{"san":"g6","uci":"g7g6","w":0,"d":0,"b":1,"r":2707},{"san":"Bf5","uci":"c8f5","w":0,"d":0,"b":1,"r":2708}],"g":["mc71421","mc84158","mc82323","mc80272","mc59389","mc59302","mc74508","mc28863","mc59390","mc59391"]},"r1bqkb1r/pppn1ppp/3p1n2/4p3/2PP4/2N1PN2/PP3PPP/R1BQKB1R b KQkq -":{"w":2,"d":3,"b":3,"r":2569,"m":[{"san":"g6","uci":"g7g6","w":1,"d":1,"b":2,"r":2588},{"san":"Be7","uci":"f8e7","w":1,"d":2,"b":1,"r":2549}],"g":["mc47562","mc49587","mc65656","mc78710","mc736","mc91447","mc14982","mc64608"]},"rnbqkb1r/pp1ppp1p/5np1/8/2PN4/2N5/PP2PPPP/R1BQKB1R b KQkq -":{"w":9,"d":17,"b":6,"r":2583,"m":[{"san":"Nc6","uci":"b8c6","w":4,"d":7,"b":2,"r":2546},{"san":"d5","uci":"d7d5","w":3,"d":6,"b":3,"r":2632},{"san":"Bg7","uci":"f8g7","w":2,"d":4,"b":1,"r":2569}],"g":["mc89167","mc82689","mc103647","mc33964","mc82674","mc73790","mc744","mc50566","mc44584","mc108355"]},"r1bqkb1r/pppp1ppp/2n2n2/4p3/2PP4/2N2N2/PP2PPPP/R1BQKB1R b KQkq -":{"w":15,"d":24,"b":13,"r":2640,"m":[{"san":"exd4","uci":"e5d4","w":10,"d":23,"b":12,"r":2640},{"san":"e4","uci":"e5e4","w":5,"d":1,"b":1,"r":2643}],"g":["mc21814","mc78849","mc21965","mc27720","mc13029","mc21812","mc35312","mc35313","mc83841","mc83843"]},"r1bqk1nr/1p3ppp/p1n5/2bp4/8/3B1N2/PPPN1PPP/R1BQ1RK1 b kq -":{"w":0,"d":2,"b":0,"r":2593,"m":[{"san":"Nf6","uci":"g8f6","w":0,"d":2,"b":0,"r":2593}],"g":["mc909","mc64851"]},"r1bqk1nr/1ppnppbp/p2p2p1/8/P2PP3/2N1BN2/1PP2PPP/R2QKB1R b KQkq -":{"w":2,"d":0,"b":0,"r":2670,"m":[{"san":"Ngf6","uci":"g8f6","w":2,"d":0,"b":0,"r":2670}],"g":["mc986","mc101809"]},"rnbqkb1r/pp3ppp/4pn2/2pp4/2PP4/2N1PN2/PP3PPP/R1BQKB1R b KQkq -":{"w":77,"d":115,"b":53,"r":2660,"m":[{"san":"Nc6","uci":"b8c6","w":48,"d":79,"b":34,"r":2643},{"san":"a6","uci":"a7a6","w":9,"d":17,"b":9,"r":2697},{"san":"dxc4","uci":"d5c4","w":11,"d":12,"b":6,"r":2713},{"san":"cxd4","uci":"c5d4","w":6,"d":5,"b":1,"r":2715},{"san":"Be7","uci":"f8e7","w":3,"d":2,"b":3,"r":2588}],"g":["mc21177","mc30981","mc19382","mc74879","mc19099","mc70814","mc19648","mc20399","mc19863","mc20294"]},"r1bqkbnr/pp2pppp/2np4/1B6/3QP3/5N2/PPP2PPP/RNB1K2R b KQkq -":{"w":21,"d":28,"b":16,"r":2654,"m":[{"san":"Bd7","uci":"c8d7","w":18,"d":25,"b":13,"r":2654},{"san":"a6","uci":"a7a6","w":1,"d":2,"b":3,"r":2686},{"san":"Qd7","uci":"d8d7","w":0,"d":1,"b":0,"r":2600},{"san":"Nf6","uci":"g8f6","w":1,"d":0,"b":0,"r":2655},{"san":"e5","uci":"e7e5","w":1,"d":0,"b":0,"r":2535}],"g":["mc75327","mc38789","mc101970","mc52625","mc39534","mc39517","mc78477","mc12935","mc12939","mc78473"]},"r1bqkb1r/pp1npppp/3p1n2/1Bp5/3PP3/2N2N2/PPP2PPP/R1BQK2R b KQkq -":{"w":9,"d":9,"b":9,"r":2643,"m":[{"san":"cxd4","uci":"c5d4","w":7,"d":8,"b":8,"r":2651},{"san":"a6","uci":"a7a6","w":2,"d":1,"b":1,"r":2594}],"g":["mc45530","mc52507","mc101862","mc7408","mc1314","mc102138","mc82110","mc52280","mc1410","mc82278"]},"rnbqk1nr/pp3ppp/4p3/2bp4/4P3/1NP5/PP3PPP/R1BQKBNR b KQkq -":{"w":0,"d":2,"b":0,"r":2608,"m":[{"san":"Bb6","uci":"c5b6","w":0,"d":2,"b":0,"r":2608}],"g":["mc1352","mc24080"]},"rnbq1rk1/pppp2pp/4pn2/5pB1/1bPP4/2N1PN2/PP3PPP/R2QKB1R b KQ -":{"w":1,"d":1,"b":0,"r":2614,"m":[{"san":"Bxc3+","uci":"b4c3","w":1,"d":0,"b":0,"r":2728},{"san":"c6","uci":"c7c6","w":0,"d":1,"b":0,"r":2500}],"g":["mc1635","mc16218"]},"r2qkbnr/pppn1ppp/4p3/8/3Pb3/3B1N2/PPP2PPP/R1BQ1RK1 w kq -":{"w":0,"d":1,"b":2,"r":2691,"m":[{"san":"Bxe4","uci":"d3e4","w":0,"d":1,"b":2,"r":2691}],"g":["mc1909","mc73724","mc46464"]},"r1bqk1nr/1p3ppp/p1n1p3/2bp4/4P3/3B1N2/PPPN1PPP/R1BQ1RK1 b kq -":{"w":3,"d":4,"b":2,"r":2654,"m":[{"san":"Nge7","uci":"g8e7","w":2,"d":3,"b":0,"r":2645},{"san":"Nf6","uci":"g8f6","w":1,"d":1,"b":2,"r":2665}],"g":["mc6026","mc108543","mc23524","mc1998","mc22401","mc2114","mc101709","mc64802","mc15983"]},"rnbq1rk1/pp3ppp/4pn2/2bp4/2P2B2/2N2N2/PP2PPPP/2RQKB1R w K -":{"w":1,"d":5,"b":0,"r":2679,"m":[{"san":"e3","uci":"e2e3","w":1,"d":4,"b":0,"r":2713},{"san":"cxd5","uci":"c4d5","w":0,"d":1,"b":0,"r":2510}],"g":["mc38881","mc46567","mc38915","mc2136","mc10357","mc100249"]},"r2qkbnr/1p1bpppp/p2p4/8/3QP3/5N2/PPP2PPP/RNB2RK1 b kq -":{"w":1,"d":19,"b":4,"r":2720,"m":[{"san":"e5","uci":"e7e5","w":0,"d":8,"b":3,"r":2731},{"san":"Nf6","uci":"g8f6","w":0,"d":6,"b":1,"r":2740},{"san":"Rc8","uci":"a8c8","w":1,"d":5,"b":0,"r":2678}],"g":["mc7732","mc109828","mc7992","mc34560","mc35161","mc83751","mc7919","mc109979","mc8348","mc83388"]},"rnbqkb1r/ppp2ppp/8/3n4/2B2p2/5N2/PPPP2PP/RNBQK2R w KQkq -":{"w":5,"d":4,"b":3,"r":2696,"m":[{"san":"O-O","uci":"e1g1","w":4,"d":4,"b":1,"r":2717},{"san":"Bxd5","uci":"c4d5","w":1,"d":0,"b":2,"r":2634}],"g":["mc10689","mc18831","mc18284","mc2241","mc74067","mc68580","mc102055","mc50460","mc101911","mc98824"]},"rnb1kb1r/pp3ppp/4pn2/2Pq4/8/8/PPPN1PPP/R1BQKBNR w KQkq -":{"w":3,"d":6,"b":8,"r":2688,"m":[{"san":"Ngf3","uci":"g1f3","w":3,"d":5,"b":4,"r":2695},{"san":"Nb3","uci":"d2b3","w":0,"d":1,"b":4,"r":2670}],"g":["mc13612","mc80439","mc41771","mc78596","mc61541","mc2607","mc84468","mc78569","mc41889","mc41464"]},"rn1qkb1r/pp2pppp/2p2n2/3p4/2PP2b1/4PN1P/PP3PP1/RNBQKB1R b KQkq -":{"w":50,"d":52,"b":32,"r":2706,"m":[{"san":"Bxf3","uci":"g4f3","w":28,"d":26,"b":14,"r":2703},{"san":"Bh5","uci":"g4h5","w":22,"d":25,"b":18,"r":2708},{"san":"Bf5","uci":"g4f5","w":0,"d":1,"b":0,"r":2758}],"g":["mc31032","mc21243","mc74645","mc18907","mc20944","mc30010","mc19323","mc34230","mc7735","mc109975"]},"r1bqk2r/ppp2ppp/2p2n2/2b1p3/4P3/3P1N2/PPP2PPP/RNBQ1RK1 b kq -":{"w":43,"d":54,"b":39,"r":2745,"m":[{"san":"Nd7","uci":"f6d7","w":24,"d":28,"b":13,"r":2746},{"san":"Bd6","uci":"c5d6","w":11,"d":8,"b":11,"r":2751},{"san":"Qe7","uci":"d8e7","w":2,"d":12,"b":8,"r":2729},{"san":"Bg4","uci":"c8g4","w":4,"d":3,"b":7,"r":2745},{"san":"Qd6","uci":"d8d6","w":2,"d":3,"b":0,"r":2780}],"g":["mc20028","mc35916","mc21108","mc78535","mc21613","mc21437","mc8019","mc21058","mc21060","mc89906"]},"r1bqkbnr/pp1p1p1p/2n3p1/2p1p3/2P5/2N2NP1/PP1PPPBP/R1BQK2R b KQkq -":{"w":8,"d":20,"b":12,"r":2746,"m":[{"san":"Bg7","uci":"f8g7","w":8,"d":20,"b":12,"r":2746}],"g":["mc18572","mc61075","mc10903","mc21860","mc39556","mc74571","mc10141","mc38867","mc103726","mc39344"]},"r2qkb1r/pp1bpppp/2np1n2/1B6/2PNP3/2N5/PP3PPP/R1BQK2R b KQkq -":{"w":0,"d":3,"b":1,"r":2695,"m":[{"san":"g6","uci":"g7g6","w":0,"d":3,"b":1,"r":2695}],"g":["mc84503","mc31009","mc3221","mc94707"]},"r1bqkbnr/pp3ppp/2n1p3/2pp4/3PP3/2P2N2/PP1N1PPP/R1BQKB1R b KQkq -":{"w":0,"d":1,"b":1,"r":2550,"m":[{"san":"cxd4","uci":"c5d4","w":0,"d":0,"b":1,"r":2600},{"san":"Nf6","uci":"g8f6","w":0,"d":1,"b":0,"r":2500}],"g":["mc3377","mc37490"]},"rnbqk2r/ppp1bppp/4pn2/8/3PP3/2NB1N2/PP3PPP/R1BQK2R b KQkq -":{"w":0,"d":2,"b":1,"r":2600,"m":[{"san":"c5","uci":"c7c5","w":0,"d":1,"b":1,"r":2600},{"san":"Nbd7","uci":"b8d7","w":0,"d":1,"b":0,"r":2600}],"g":["mc3661","mc4028","mc4360"]},"r1bqk2r/pp1nbppp/2p1pn2/3p2B1/2PP4/2NBPN2/PP3PPP/R2QK2R b KQkq -":{"w":15,"d":8,"b":8,"r":2624,"m":[{"san":"dxc4","uci":"d5c4","w":9,"d":3,"b":1,"r":2598},{"san":"O-O","uci":"e8g8","w":5,"d":2,"b":2,"r":2609},{"san":"h6","uci":"h7h6","w":1,"d":3,"b":3,"r":2710},{"san":"a6","uci":"a7a6","w":0,"d":0,"b":2,"r":2550}],"g":["mc20117","mc35350","mc21352","mc21361","mc40829","mc38501","mc3738","mc3780","mc3784","mc4178"]},"r2qkbnr/ppp1pppp/2n5/3p4/Q1PP2b1/5N2/PP2PPPP/RNB1KB1R b KQkq -":{"w":2,"d":1,"b":1,"r":2581,"m":[{"san":"Bxf3","uci":"g4f3","w":2,"d":1,"b":1,"r":2581}],"g":["mc97682","mc3758","mc3858","mc15175"]},"rn1qkb1r/p3pppp/1p3n2/3p4/2PN4/6P1/PP2PPKP/RNBQ1R2 b kq -":{"w":2,"d":0,"b":0,"r":2700,"m":[{"san":"e6","uci":"e7e6","w":2,"d":0,"b":0,"r":2700}],"g":["mc3954","mc17007"]},"rnbq1rk1/pp2ppbp/2p2np1/3p4/2PP4/5NP1/PP2PPBP/RNBQ1RK1 w - -":{"w":96,"d":147,"b":63,"r":2706,"m":[{"san":"Qb3","uci":"d1b3","w":33,"d":41,"b":18,"r":2728},{"san":"cxd5","uci":"c4d5","w":14,"d":31,"b":15,"r":2652},{"san":"b3","uci":"b2b3","w":13,"d":29,"b":12,"r":2708},{"san":"Nbd2","uci":"b1d2","w":5,"d":18,"b":6,"r":2714},{"san":"Ne5","uci":"f3e5","w":7,"d":8,"b":4,"r":2731},{"san":"a4","uci":"a2a4","w":8,"d":6,"b":4,"r":2712},{"san":"Nc3","uci":"b1c3","w":12,"d":2,"b":1,"r":2732},{"san":"Qa4","uci":"d1a4","w":2,"d":9,"b":3,"r":2700},{"san":"Na3","uci":"b1a3","w":1,"d":2,"b":0,"r":2600},{"san":"Re1","uci":"f1e1","w":1,"d":1,"b":0,"r":2769}],"g":["mc30666","mc20138","mc81084","mc23614","mc7318","mc18297","mc10118","mc72005","mc72043","mc18389"]},"rnbqkb1r/pp3ppp/2p1pn2/6B1/2pP4/2N2N2/PP2PPPP/R2QKB1R w KQkq -":{"w":62,"d":68,"b":35,"r":2663,"m":[{"san":"e4","uci":"e2e4","w":57,"d":60,"b":31,"r":2663},{"san":"a4","uci":"a2a4","w":5,"d":8,"b":4,"r":2668}],"g":["mc10385","mc61188","mc61054","mc10577","mc74472","mc7676","mc61312","mc74807","mc34432","mc109451"]},"rnbqk2r/ppp2ppp/3b4/3pN3/3Pn3/3B4/PPP2PPP/RNBQ1RK1 b kq -":{"w":7,"d":12,"b":0,"r":2648,"m":[{"san":"O-O","uci":"e8g8","w":7,"d":11,"b":0,"r":2643},{"san":"Nc6","uci":"b8c6","w":0,"d":1,"b":0,"r":2738}],"g":["mc52264","mc13132","mc5212","mc51982","mc43856","mc51992","mc92572","mc48216","mc106781","mc92365"]},"r2qkb1r/pp1n1ppp/2p1p3/3n1b2/2BP4/4PN2/PP2QPPP/RNB2RK1 b kq -":{"w":0,"d":2,"b":0,"r":2600,"m":[{"san":"Bg4","uci":"f5g4","w":0,"d":2,"b":0,"r":2600}],"g":["mc4549","mc31921"]},"rnbqkb1r/pp3ppp/5n2/2pp4/3P4/2N1PN2/PP3PPP/R1BQKB1R b KQkq -":{"w":13,"d":7,"b":4,"r":2658,"m":[{"san":"Nc6","uci":"b8c6","w":12,"d":6,"b":3,"r":2662},{"san":"a6","uci":"a7a6","w":1,"d":1,"b":1,"r":2627}],"g":["mc8292","mc70646","mc8232","mc40437","mc62478","mc78128","mc42084","mc78519","mc84632","mc78158"]},"rnbqkbnr/ppp2ppp/4p3/3p4/3P4/4P3/PPPN1PPP/R1BQKBNR b KQkq -":{"w":0,"d":1,"b":1,"r":2550,"m":[{"san":"c5","uci":"c7c5","w":0,"d":1,"b":1,"r":2550}],"g":["mc4774","mc101372"]},"rnbqk2r/1p2ppbp/p2p1np1/8/3NP3/2N1BP2/PPPQ2PP/R3KB1R b KQkq -":{"w":5,"d":4,"b":4,"r":2723,"m":[{"san":"h5","uci":"h7h5","w":3,"d":1,"b":2,"r":2771},{"san":"b5","uci":"b7b5","w":0,"d":2,"b":1,"r":2763},{"san":"Nbd7","uci":"b8d7","w":1,"d":1,"b":1,"r":2628},{"san":"Nc6","uci":"b8c6","w":1,"d":0,"b":0,"r":2600}],"g":["mc20270","mc40764","mc20483","mc22076","mc61607","mc75055","mc81032","mc77679","mc73722","mc73497"]},"rnbqk2r/ppppppbp/5np1/8/2P5/2N3P1/PP1PPPBP/R1BQK1NR b KQkq -":{"w":63,"d":77,"b":49,"r":2640,"m":[{"san":"O-O","uci":"e8g8","w":56,"d":65,"b":41,"r":2639},{"san":"d6","uci":"d7d6","w":3,"d":4,"b":5,"r":2640},{"san":"c5","uci":"c7c5","w":2,"d":7,"b":0,"r":2641},{"san":"c6","uci":"c7c6","w":0,"d":1,"b":2,"r":2689},{"san":"e5","uci":"e7e5","w":1,"d":0,"b":1,"r":2669},{"san":"e6","uci":"e7e6","w":1,"d":0,"b":0,"r":2600}],"g":["mc21140","mc71902","mc29179","mc23905","mc23652","mc61126","mc74271","mc84251","mc71604","mc61223"]},"rn1qkb1r/pbpp1ppp/1p2pn2/8/2P1P3/2NB1N2/PP1P1PPP/R1BQK2R b KQkq -":{"w":6,"d":3,"b":0,"r":2609,"m":[{"san":"c5","uci":"c7c5","w":4,"d":3,"b":0,"r":2622},{"san":"Bb4","uci":"f8b4","w":1,"d":0,"b":0,"r":2560},{"san":"d6","uci":"d7d6","w":1,"d":0,"b":0,"r":2565}],"g":["mc49998","mc56289","mc56157","mc56165","mc5150","mc87545","mc107198","mc56222","mc56253"]},"rnbqk2r/pp1p1ppp/4pn2/8/1bPp4/2N1P3/PP2NPPP/R1BQKB1R w KQkq -":{"w":21,"d":28,"b":5,"r":2638,"m":[{"san":"exd4","uci":"e3d4","w":21,"d":28,"b":5,"r":2638}],"g":["mc66533","mc59980","mc35587","mc6219","mc24547","mc6250","mc6117","mc28176","mc5883","mc9531"]},"rn1qkb1r/p1pp1ppp/b3pn2/8/3P4/1PN2NP1/P3PPBP/R1BQK2R b KQkq -":{"w":2,"d":2,"b":0,"r":2721,"m":[{"san":"d5","uci":"d7d5","w":2,"d":2,"b":0,"r":2721}],"g":["mc5849","mc49970","mc5887","mc17806"]},"r2qk2r/pppb1ppp/3b4/3p4/2PPn3/3B4/PP3PPP/RNBQ1RK1 b kq -":{"w":7,"d":19,"b":6,"r":2713,"m":[{"san":"c6","uci":"c7c6","w":7,"d":16,"b":5,"r":2711},{"san":"O-O","uci":"e8g8","w":0,"d":3,"b":1,"r":2726}],"g":["mc7185","mc60703","mc85335","mc85340","mc59698","mc92636","mc6934","mc93704","mc6088","mc6090"]},"rn1qkbnr/pp2pppb/2p4p/7P/3P4/5NN1/PPP2PP1/R1BQKB1R b KQkq -":{"w":4,"d":3,"b":2,"r":2626,"m":[{"san":"Nd7","uci":"b8d7","w":2,"d":3,"b":0,"r":2609},{"san":"Nf6","uci":"g8f6","w":1,"d":0,"b":1,"r":2618},{"san":"e6","uci":"e7e6","w":1,"d":0,"b":1,"r":2679}],"g":["mc45866","mc48141","mc99756","mc5997","mc57646","mc51239","mc86110","mc107734","mc15988"]},"rnbqkbnr/ppp1pp1p/6p1/8/2Pp4/3P1NP1/PP2PP1P/RNBQKB1R b KQkq -":{"w":2,"d":0,"b":0,"r":2749,"m":[{"san":"Bg7","uci":"f8g7","w":2,"d":0,"b":0,"r":2749}],"g":["mc6027","mc101950"]},"rnbqkb1r/pp2pp1p/2pp1np1/8/3PP3/2N1BP2/PPP3PP/R2QKBNR b KQkq -":{"w":6,"d":6,"b":4,"r":2619,"m":[{"san":"b5","uci":"b7b5","w":4,"d":3,"b":3,"r":2638},{"san":"Nbd7","uci":"b8d7","w":2,"d":0,"b":1,"r":2641},{"san":"Qb6","uci":"d8b6","w":0,"d":3,"b":0,"r":2535}],"g":["mc6114","mc70799","mc22420","mc6234","mc70368","mc68860","mc108164","mc22994","mc23415","mc14901"]},"r1b1kb1r/ppqppppp/2n2n2/8/3NP3/2N5/PPP1BPPP/R1BQK2R b KQkq -":{"w":0,"d":2,"b":1,"r":2707,"m":[{"san":"e6","uci":"e7e6","w":0,"d":2,"b":1,"r":2707}],"g":["mc6191","mc52723","mc55111"]},"r1b1k2r/ppp1qppp/2p2n2/4p3/4P3/3PPN2/PPPN2PP/R2QK2R b KQkq -":{"w":0,"d":2,"b":0,"r":2748,"m":[{"san":"O-O","uci":"e8g8","w":0,"d":2,"b":0,"r":2748}],"g":["mc6511","mc108933"]},"r1bqnrk1/pp1pppbp/2B3p1/2p1P3/8/2NP1N2/PPP2PPP/R1BQ1RK1 b - -":{"w":2,"d":4,"b":1,"r":2751,"m":[{"san":"dxc6","uci":"d7c6","w":2,"d":3,"b":1,"r":2752},{"san":"bxc6","uci":"b7c6","w":0,"d":1,"b":0,"r":2744}],"g":["mc12268","mc20923","mc6614","mc12472","mc84437","mc12483","mc68315"]},"rnb1kb1r/ppp2pp1/4pq1p/3p4/3PP3/5N2/PPPN1PPP/R2QKB1R b KQkq -":{"w":0,"d":2,"b":1,"r":2725,"m":[{"san":"g6","uci":"g7g6","w":0,"d":1,"b":1,"r":2706},{"san":"Qd8","uci":"f6d8","w":0,"d":1,"b":0,"r":2765}],"g":["mc81320","mc77583","mc6675"]},"r1bqkb1r/pp2pppp/2np1n2/8/2PNP3/5P2/PP4PP/RNBQKB1R b KQkq -":{"w":2,"d":6,"b":4,"r":2637,"m":[{"san":"e6","uci":"e7e6","w":0,"d":4,"b":3,"r":2633},{"san":"g6","uci":"g7g6","w":1,"d":2,"b":0,"r":2669},{"san":"e5","uci":"e7e5","w":0,"d":0,"b":1,"r":2632},{"san":"Qb6","uci":"d8b6","w":1,"d":0,"b":0,"r":2570}],"g":["mc20670","mc40872","mc7055","mc110181","mc35450","mc17273","mc32796","mc32807","mc53312","mc9041"]},"rn1qkb1r/pp2pppp/2p3b1/7n/2BP3P/5NN1/PPP2PP1/R1BQK2R b KQkq -":{"w":0,"d":3,"b":0,"r":2755,"m":[{"san":"e6","uci":"e7e6","w":0,"d":2,"b":0,"r":2775},{"san":"Nd7","uci":"b8d7","w":0,"d":1,"b":0,"r":2714}],"g":["mc7072","mc45305","mc7200"]},"r1bq1rk1/pppp1ppp/1bn2n2/1B2P3/4P3/2P2N2/PP3PPP/RNBQ1RK1 b - -":{"w":2,"d":11,"b":3,"r":2636,"m":[{"san":"Nxe4","uci":"f6e4","w":2,"d":11,"b":3,"r":2636}],"g":["mc93996","mc109446","mc7289","mc67463","mc103291","mc66558","mc15639","mc98965","mc98974","mc99030"]},"rn1qkb1r/pb1pnppp/1p2p3/2p5/4P3/1P1B1N2/P1PP1PPP/RNBQR1K1 b kq -":{"w":1,"d":1,"b":0,"r":2748,"m":[{"san":"Ng6","uci":"e7g6","w":1,"d":1,"b":0,"r":2748}],"g":["mc18294","mc7316"]},"rnbqk2r/pp3pbp/3p1np1/2pP4/8/2N2NP1/PP2PPBP/R1BQK2R b KQkq -":{"w":28,"d":34,"b":25,"r":2648,"m":[{"san":"O-O","uci":"e8g8","w":28,"d":34,"b":25,"r":2648}],"g":["mc9983","mc109477","mc61089","mc24823","mc109668","mc30312","mc30314","mc10050","mc45846","mc13563"]},"rn1qkb1r/1p2pppp/p1p2n2/3p4/2PP4/2NbPN2/PP3PPP/R1BQK2R w KQkq -":{"w":2,"d":12,"b":0,"r":2742,"m":[{"san":"Qxd3","uci":"d1d3","w":2,"d":12,"b":0,"r":2742}],"g":["mc10475","mc109753","mc18645","mc7455","mc60086","mc30202","mc88607","mc102902","mc102661","mc89922"]},"r2qkbnr/pp1npppp/3p4/2p5/2P1P3/5N2/PP1P1PPP/RNBQK2R b KQkq -":{"w":0,"d":0,"b":2,"r":2758,"m":[{"san":"Ne5","uci":"d7e5","w":0,"d":0,"b":2,"r":2758}],"g":["mc7628","mc82610"]},"r1bqk1nr/2pnppbp/p2p2p1/1p2P3/3P1P2/2NB1N2/PPP3PP/R1BQK2R b KQkq -":{"w":4,"d":4,"b":3,"r":2702,"m":[{"san":"c5","uci":"c7c5","w":1,"d":2,"b":2,"r":2739},{"san":"Bb7","uci":"c8b7","w":2,"d":2,"b":1,"r":2677},{"san":"Nb6","uci":"d7b6","w":1,"d":0,"b":0,"r":2640}],"g":["mc7672","mc22149","mc25099","mc79229","mc25089","mc75300","mc37809","mc23534","mc38051","mc102252"]},"r1bqk1nr/p2nppbp/2pp2p1/1p2P3/3P1P2/2NB1N2/PPP3PP/R1BQK2R b KQkq -":{"w":2,"d":0,"b":0,"r":2804,"m":[{"san":"Nb6","uci":"d7b6","w":2,"d":0,"b":0,"r":2804}],"g":["mc7701","mc25138"]},"rn1qkb1r/pp2pppp/2p2n2/3p1b2/3P1B2/2N1PN2/PPP2PPP/R2QKB1R b KQkq -":{"w":1,"d":0,"b":2,"r":2657,"m":[{"san":"e6","uci":"e7e6","w":1,"d":0,"b":1,"r":2652},{"san":"h6","uci":"h7h6","w":0,"d":0,"b":1,"r":2666}],"g":["mc89227","mc95366","mc7937"]},"rnbqk2r/pp1pppbp/5np1/2p5/2P5/2N1P1P1/PP1P1PBP/R1BQK1NR b KQkq -":{"w":9,"d":8,"b":9,"r":2677,"m":[{"san":"O-O","uci":"e8g8","w":7,"d":3,"b":5,"r":2659},{"san":"e6","uci":"e7e6","w":2,"d":3,"b":4,"r":2703},{"san":"Nc6","uci":"b8c6","w":0,"d":1,"b":0,"r":2767},{"san":"d6","uci":"d7d6","w":0,"d":1,"b":0,"r":2618}],"g":["mc7976","mc61576","mc24978","mc39336","mc40498","mc83658","mc39265","mc29772","mc29774","mc46211"]},"r2qkbnr/pp1n1ppp/2p1p1b1/3pP3/3P4/5N2/PPPNBPPP/R1BQ1RK1 b kq -":{"w":8,"d":6,"b":2,"r":2696,"m":[{"san":"Nh6","uci":"g8h6","w":7,"d":6,"b":2,"r":2696},{"san":"Be7","uci":"f8e7","w":1,"d":0,"b":0,"r":2701}],"g":["mc39594","mc39509","mc18025","mc24904","mc8175","mc67433","mc46802","mc102649","mc40413","mc102736"]},"r1b1k2r/ppp1qppp/2p2n2/2b1p3/4P3/3P1N1P/PPP1QPP1/RNB1K2R b KQkq -":{"w":1,"d":2,"b":0,"r":2770,"m":[{"san":"Bd6","uci":"c5d6","w":0,"d":2,"b":0,"r":2769},{"san":"h6","uci":"h7h6","w":1,"d":0,"b":0,"r":2771}],"g":["mc21277","mc8424","mc11564"]},"r1bqkb1r/ppp2p2/2np1n1p/4p1p1/2B1P3/2PP1N2/PP3PPP/R1BQKN1R b KQkq -":{"w":2,"d":0,"b":2,"r":2738,"m":[{"san":"g4","uci":"g5g4","w":2,"d":0,"b":1,"r":2765},{"san":"Bg7","uci":"f8g7","w":0,"d":0,"b":1,"r":2659}],"g":["mc8538","mc26166","mc26044","mc71178"]},"rnbqkb1r/1p3ppp/p3pn2/8/3N4/4P3/PP2BPPP/RNBQ1RK1 b kq -":{"w":3,"d":2,"b":1,"r":2702,"m":[{"san":"Be7","uci":"f8e7","w":1,"d":2,"b":1,"r":2707},{"san":"Bd6","uci":"f8d6","w":2,"d":0,"b":0,"r":2692}],"g":["mc27040","mc85023","mc8869","mc8813","mc27345","mc47621"]},"rnbqkb1r/1p2pppp/p2p1n2/8/3NP3/2NQ4/PPP2PPP/R1B1KB1R b KQkq -":{"w":6,"d":8,"b":6,"r":2727,"m":[{"san":"Nbd7","uci":"b8d7","w":3,"d":3,"b":3,"r":2744},{"san":"e6","uci":"e7e6","w":2,"d":3,"b":2,"r":2724},{"san":"g6","uci":"g7g6","w":1,"d":1,"b":0,"r":2639},{"san":"Nc6","uci":"b8c6","w":0,"d":1,"b":1,"r":2755}],"g":["mc20506","mc26247","mc30541","mc20772","mc28447","mc36941","mc20474","mc28464","mc36930","mc39363"]},"rnbq1rk1/pp2ppbp/5np1/2p3B1/2B1P3/2P2N2/PP1N1PPP/R2QK2R b KQ -":{"w":5,"d":7,"b":4,"r":2659,"m":[{"san":"Nc6","uci":"b8c6","w":3,"d":6,"b":4,"r":2658},{"san":"a6","uci":"a7a6","w":1,"d":0,"b":0,"r":2650},{"san":"h6","uci":"h7h6","w":0,"d":1,"b":0,"r":2590},{"san":"Qc7","uci":"d8c7","w":1,"d":0,"b":0,"r":2752}],"g":["mc18662","mc83621","mc20257","mc17908","mc88585","mc71234","mc28420","mc17892","mc51937","mc11840"]},"r1bqkb1r/1p1n1ppp/p1p1pn2/3p4/2PP4/1PN1PN2/P1Q2PPP/R1B1KB1R b KQkq -":{"w":5,"d":5,"b":5,"r":2686,"m":[{"san":"Bd6","uci":"f8d6","w":3,"d":5,"b":2,"r":2723},{"san":"b5","uci":"b7b5","w":0,"d":0,"b":2,"r":2612},{"san":"b6","uci":"b7b6","w":2,"d":0,"b":0,"r":2550},{"san":"Bb4","uci":"f8b4","w":0,"d":0,"b":1,"r":2743}],"g":["mc18756","mc34098","mc69820","mc69825","mc69824","mc80315","mc70081","mc9470","mc67532","mc46924"]},"rnbqkbnr/1p1p1ppp/p3p3/8/3N4/2N3P1/PPP1PP1P/R1BQKB1R b KQkq -":{"w":2,"d":0,"b":0,"r":2759,"m":[{"san":"Qc7","uci":"d8c7","w":2,"d":0,"b":0,"r":2759}],"g":["mc9526","mc102686"]},"r1bqk2r/ppp1b1pp/2np1n2/1B2p3/4P3/P1N2N2/1PP2PPP/R1BQ1RK1 b kq -":{"w":2,"d":0,"b":0,"r":2762,"m":[{"san":"O-O","uci":"e8g8","w":2,"d":0,"b":0,"r":2762}],"g":["mc10100","mc103365"]},"rn1qk2r/ppp1bppp/5n2/3p1b2/3P1B2/1QN1P3/PP3PPP/R3KBNR b KQkq -":{"w":4,"d":3,"b":3,"r":2743,"m":[{"san":"Nc6","uci":"b8c6","w":4,"d":3,"b":3,"r":2743}],"g":["mc10130","mc60957","mc75188","mc110050","mc52421","mc108301","mc45598","mc69345","mc41840","mc42782"]},"r1bqk2r/pppnppbp/6p1/8/Q2PP3/2P2N2/P4PPP/R1B1KB1R b KQkq -":{"w":4,"d":11,"b":5,"r":2736,"m":[{"san":"O-O","uci":"e8g8","w":4,"d":7,"b":4,"r":2725},{"san":"c5","uci":"c7c5","w":0,"d":4,"b":1,"r":2769}],"g":["mc19764","mc83553","mc74818","mc74822","mc74825","mc74829","mc18486","mc24731","mc10270","mc12372"]},"r1bqkb1r/pppn1pp1/4pn1p/3p4/2PP3B/2N1P3/PP3PPP/R2QKBNR b KQkq -":{"w":4,"d":0,"b":1,"r":2708,"m":[{"san":"Bb4","uci":"f8b4","w":2,"d":0,"b":0,"r":2801},{"san":"Be7","uci":"f8e7","w":1,"d":0,"b":1,"r":2669},{"san":"c6","uci":"c7c6","w":1,"d":0,"b":0,"r":2600}],"g":["mc10451","mc74353","mc46729","mc28700","mc65280"]},"rnbqkb1r/pppppp1p/5np1/6B1/2PP4/8/PP2PPPP/RN1QKBNR b KQkq -":{"w":11,"d":12,"b":7,"r":2708,"m":[{"san":"Bg7","uci":"f8g7","w":8,"d":6,"b":7,"r":2694},{"san":"Ne4","uci":"f6e4","w":2,"d":5,"b":0,"r":2762},{"san":"d5","uci":"d7d5","w":1,"d":1,"b":0,"r":2661}],"g":["mc25094","mc34126","mc10533","mc69791","mc25199","mc69990","mc69950","mc70198","mc104076","mc70010"]},"rnb1kb1r/pp1p1ppp/4pn2/q3P1B1/3p4/8/PPPN1PPP/R2QKBNR w KQkq -":{"w":0,"d":2,"b":0,"r":2782,"m":[{"san":"Nf3","uci":"g1f3","w":0,"d":2,"b":0,"r":2782}],"g":["mc10583","mc74478"]},"rnbqk2r/pp3pbp/3p1np1/2pP4/4P3/2N2P2/PP2N1PP/R1BQKB1R b KQkq -":{"w":7,"d":14,"b":5,"r":2764,"m":[{"san":"a6","uci":"a7a6","w":3,"d":9,"b":1,"r":2770},{"san":"O-O","uci":"e8g8","w":2,"d":2,"b":4,"r":2741},{"san":"Nbd7","uci":"b8d7","w":2,"d":3,"b":0,"r":2784}],"g":["mc53117","mc74715","mc19632","mc83416","mc30468","mc83602","mc30236","mc40322","mc30258","mc83438"]},"r1bq1rk1/p1p1bppp/1pn1pn2/3p4/3P4/5NP1/PPPNPPBP/R1BQ1RK1 w - -":{"w":4,"d":0,"b":0,"r":2773,"m":[{"san":"b3","uci":"b2b3","w":3,"d":0,"b":0,"r":2782},{"san":"Re1","uci":"f1e1","w":1,"d":0,"b":0,"r":2747}],"g":["mc21113","mc84353","mc81143","mc10792"]},"r1bqkb1r/pppnpppp/5n2/3p4/8/5NP1/PPPPPPBP/RNBQ1RK1 b kq -":{"w":0,"d":1,"b":1,"r":2619,"m":[{"san":"e5","uci":"e7e5","w":0,"d":1,"b":1,"r":2619}],"g":["mc97694","mc10926"]},"rnbqkbnr/pp2pppp/2p5/3p4/2P5/6P1/PP1PPPBP/RNBQK1NR b KQkq -":{"w":4,"d":3,"b":1,"r":2655,"m":[{"san":"Nf6","uci":"g8f6","w":2,"d":3,"b":1,"r":2706},{"san":"g6","uci":"g7g6","w":2,"d":0,"b":0,"r":2500}],"g":["mc10948","mc19131","mc10964","mc18076","mc63649","mc105119","mc55749","mc63518"]},"rnbq1rk1/pp2bppp/3p1n2/2pPp3/4P3/2N5/PPPBBPPP/R2QK1NR b KQ -":{"w":2,"d":0,"b":0,"r":2813,"m":[{"san":"Nbd7","uci":"b8d7","w":2,"d":0,"b":0,"r":2813}],"g":["mc11038","mc19265"]},"r2qkb1r/ppp3pp/2np1n2/4p3/2B1P1b1/5N1P/PPP2PP1/RNBQ1RK1 b kq -":{"w":2,"d":0,"b":2,"r":2825,"m":[{"san":"Bh5","uci":"g4h5","w":2,"d":0,"b":2,"r":2825}],"g":["mc19753","mc26133","mc11503","mc25935"]},"rnbqkb1r/p4ppp/1p2pn2/2pp4/3P4/1P2PN2/PBPN1PPP/R2QKB1R b KQkq -":{"w":1,"d":1,"b":0,"r":2742,"m":[{"san":"Bb7","uci":"c8b7","w":1,"d":0,"b":0,"r":2758},{"san":"Be7","uci":"f8e7","w":0,"d":1,"b":0,"r":2725}],"g":["mc11614","mc13618"]},"rnbq1rk1/pp2ppbp/3p1np1/8/1P1P4/P4N2/1BPN1PPP/R2QKB1R b KQ -":{"w":0,"d":2,"b":0,"r":2783,"m":[{"san":"d5","uci":"d6d5","w":0,"d":2,"b":0,"r":2783}],"g":["mc12001","mc84025"]},"rnbqkb1r/pp1p2pp/4p3/2pnPp2/8/2N2N2/PPPP1PPP/R1BQKB1R b KQkq -":{"w":2,"d":1,"b":7,"r":2666,"m":[{"san":"Ne7","uci":"d5e7","w":1,"d":1,"b":4,"r":2644},{"san":"Nb4","uci":"d5b4","w":0,"d":0,"b":2,"r":2693},{"san":"Nxc3","uci":"d5c3","w":1,"d":0,"b":0,"r":2754},{"san":"Nb6","uci":"d5b6","w":0,"d":0,"b":1,"r":2658}],"g":["mc27862","mc28784","mc31080","mc71253","mc36159","mc12065","mc12067","mc12069","mc35246","mc35346"]},"r1bq1rk1/pp1nppbp/3p1np1/P1p5/3P4/5NP1/1PP1PPBP/RNBQ1RK1 w - -":{"w":0,"d":0,"b":3,"r":2720,"m":[{"san":"c4","uci":"c2c4","w":0,"d":0,"b":2,"r":2776},{"san":"Nc3","uci":"b1c3","w":0,"d":0,"b":1,"r":2607}],"g":["mc12198","mc71534","mc71539"]},"rnbq1rk1/p4ppp/3ppn2/1ppP4/1bP1PN2/2N2P2/PP4PP/R1BQKB1R b KQ -":{"w":1,"d":2,"b":6,"r":2723,"m":[{"san":"e5","uci":"e6e5","w":1,"d":0,"b":3,"r":2698},{"san":"exd5","uci":"e6d5","w":0,"d":2,"b":2,"r":2756},{"san":"a6","uci":"a7a6","w":0,"d":0,"b":1,"r":2691}],"g":["mc39555","mc109823","mc12357","mc71687","mc26630","mc72764","mc71697","mc109646","mc91867"]},"rnbq1rk1/pp3pbp/3p1np1/2pPp3/2P1P3/2NB3P/PP2NPP1/R1BQK2R b KQ -":{"w":0,"d":0,"b":5,"r":2733,"m":[{"san":"Nbd7","uci":"b8d7","w":0,"d":0,"b":4,"r":2791},{"san":"Na6","uci":"b8a6","w":0,"d":0,"b":1,"r":2500}],"g":["mc12501","mc12511","mc30888","mc30898","mc90868"]},"r1bq1rk1/2ppbppp/p1n2n2/1p2p3/P3P3/1BPP1N2/1P3PPP/RNBQK2R b KQ -":{"w":0,"d":0,"b":2,"r":2666,"m":[{"san":"b4","uci":"b5b4","w":0,"d":0,"b":1,"r":2692},{"san":"Bb7","uci":"c8b7","w":0,"d":0,"b":1,"r":2639}],"g":["mc12642","mc51133"]},"rnbq1rk1/pp2ppbp/2pp1np1/8/2PPP3/2N1BN2/PP2BPPP/R2QK2R b KQ -":{"w":2,"d":0,"b":0,"r":2755,"m":[{"san":"e5","uci":"e7e5","w":2,"d":0,"b":0,"r":2755}],"g":["mc12703","mc19309"]},"rnbqkb1r/pp3ppp/1n1pp3/4P3/3P4/1B3N2/PP3PPP/RNBQK2R b KQkq -":{"w":2,"d":7,"b":0,"r":2739,"m":[{"san":"dxe5","uci":"d6e5","w":2,"d":3,"b":0,"r":2780},{"san":"Nc6","uci":"b8c6","w":0,"d":3,"b":0,"r":2651},{"san":"Bd7","uci":"c8d7","w":0,"d":1,"b":0,"r":2793}],"g":["mc13079","mc21847","mc25382","mc20991","mc20051","mc52380","mc13778","mc12728","mc81693"]},"rnbqkb1r/pp3ppp/2p1pn2/3p4/2PP4/2N1P3/PP1B1PPP/R2QKBNR b KQkq -":{"w":1,"d":2,"b":1,"r":2726,"m":[{"san":"Nbd7","uci":"b8d7","w":1,"d":0,"b":1,"r":2730},{"san":"dxc4","uci":"d5c4","w":0,"d":1,"b":0,"r":2739},{"san":"g6","uci":"g7g6","w":0,"d":1,"b":0,"r":2704}],"g":["mc12791","mc13600","mc46794","mc103223"]},"rnbq1rk1/ppp2pbp/3p2p1/3Pp2n/2P1P3/2NB1NP1/PP3P1P/R1BQK2R b KQ -":{"w":0,"d":2,"b":0,"r":2820,"m":[{"san":"Na6","uci":"b8a6","w":0,"d":2,"b":0,"r":2820}],"g":["mc12797","mc21311"]},"r1bq1rk1/ppp2ppp/1bnp1n2/4p3/P1B1P3/2PP1N2/1P3PPP/RNBQ1RK1 w - -":{"w":2,"d":0,"b":0,"r":2701,"m":[{"san":"Nbd2","uci":"b1d2","w":2,"d":0,"b":0,"r":2701}],"g":["mc13140","mc62405"]},"r1bq1rk1/pp1nppbp/2pp1np1/8/P2P4/2N2NP1/1PP1PPBP/R1BQ1RK1 w - -":{"w":1,"d":1,"b":2,"r":2666,"m":[{"san":"a5","uci":"a4a5","w":0,"d":1,"b":1,"r":2749},{"san":"e4","uci":"e2e4","w":1,"d":0,"b":1,"r":2583}],"g":["mc21801","mc13208","mc46188","mc98148"]},"r2qkbnr/pp2pppp/2n5/3p1b2/3P1B2/2P5/PP1N1PPP/R2QKBNR b KQkq -":{"w":4,"d":1,"b":0,"r":2671,"m":[{"san":"e6","uci":"e7e6","w":3,"d":1,"b":0,"r":2686},{"san":"Nf6","uci":"g8f6","w":1,"d":0,"b":0,"r":2614}],"g":["mc35747","mc20555","mc13251","mc95026","mc26870"]},"rnbqkb1r/pp1p1ppp/4p3/2pnP3/8/P1P2N2/1P1P1PPP/RNBQKB1R b KQkq -":{"w":1,"d":3,"b":2,"r":2744,"m":[{"san":"b6","uci":"b7b6","w":1,"d":3,"b":0,"r":2792},{"san":"Nc6","uci":"b8c6","w":0,"d":0,"b":1,"r":2660},{"san":"d6","uci":"d7d6","w":0,"d":0,"b":1,"r":2633}],"g":["mc23363","mc80846","mc81609","mc81423","mc13340","mc13372"]},"r1bqkb1r/pp1p1ppp/2n1p1n1/1B6/3NP3/4B3/PPP2PPP/RN1Q1RK1 b kq -":{"w":10,"d":8,"b":1,"r":2696,"m":[{"san":"Be7","uci":"f8e7","w":9,"d":7,"b":1,"r":2701},{"san":"Qc7","uci":"d8c7","w":1,"d":1,"b":0,"r":2652}],"g":["mc75206","mc89533","mc24909","mc89136","mc85573","mc85260","mc36212","mc13347","mc104659","mc35966"]},"r1bqk2r/p3bppp/2n1pn2/1ppp2B1/4P3/3P1NP1/PPP1QPBP/RN3RK1 b kq -":{"w":0,"d":2,"b":0,"r":2763,"m":[{"san":"O-O","uci":"e8g8","w":0,"d":2,"b":0,"r":2763}],"g":["mc13486","mc28227"]},"rnbqkb1r/1p3ppp/p3pn2/3p4/2PP4/1P3N2/P2N1PPP/R1BQKB1R b KQkq -":{"w":0,"d":1,"b":2,"r":2716,"m":[{"san":"b6","uci":"b7b6","w":0,"d":0,"b":2,"r":2766},{"san":"Nc6","uci":"b8c6","w":0,"d":1,"b":0,"r":2615}],"g":["mc13789","mc28843","mc57367"]},"r1b1kbnr/pp3ppp/1qn1p3/2ppP3/3P4/2PB1N2/PP3PPP/RNBQK2R b KQkq -":{"w":5,"d":2,"b":3,"r":2602,"m":[{"san":"cxd4","uci":"c5d4","w":4,"d":2,"b":3,"r":2603},{"san":"Bd7","uci":"c8d7","w":1,"d":0,"b":0,"r":2592}],"g":["mc20285","mc13889","mc41832","mc34787","mc62563","mc85178","mc96068","mc58824","mc87907","mc101347"]},"rn1qk2r/pp3ppp/2p2n2/3p1bB1/1b1P4/2N1P3/PP3PPP/2RQKBNR w Kkq -":{"w":2,"d":0,"b":0,"r":2775,"m":[{"san":"Ne2","uci":"g1e2","w":2,"d":0,"b":0,"r":2775}],"g":["mc13959","mc81241"]},"r2qkb1r/pppnpppp/5n2/3p4/6b1/1P3NP1/PBPPPPBP/RN1QK2R b KQkq -":{"w":6,"d":4,"b":1,"r":2663,"m":[{"san":"e6","uci":"e7e6","w":6,"d":4,"b":1,"r":2663}],"g":["mc61702","mc75330","mc75245","mc36915","mc76246","mc95012","mc95976","mc14127","mc95982","mc107530"]},"r1bq1rk1/pppp1ppp/2n1pn2/8/1bPP4/PQN2N2/1P2PPPP/R1B1KB1R b KQ -":{"w":2,"d":0,"b":0,"r":2550,"m":[{"san":"Bxc3+","uci":"b4c3","w":2,"d":0,"b":0,"r":2550}],"g":["mc14158","mc32326"]},"rn1qkbnr/pp1b1ppp/8/1Bpp4/3P4/8/PPPNQPPP/R1B1K1NR b KQkq -":{"w":4,"d":21,"b":3,"r":2614,"m":[{"san":"Be7","uci":"f8e7","w":4,"d":14,"b":3,"r":2614},{"san":"Qe7","uci":"d8e7","w":0,"d":7,"b":0,"r":2613}],"g":["mc93830","mc49670","mc48352","mc48358","mc56200","mc56206","mc48390","mc107009","mc56258","mc107017"]},"rnbqk2r/pp2bppp/4pn2/3p2B1/2PP4/2N2N2/PP3PPP/R2QKB1R b KQkq -":{"w":5,"d":1,"b":0,"r":2581,"m":[{"san":"O-O","uci":"e8g8","w":3,"d":1,"b":0,"r":2575},{"san":"dxc4","uci":"d5c4","w":1,"d":0,"b":0,"r":2600},{"san":"Nc6","uci":"b8c6","w":1,"d":0,"b":0,"r":2583}],"g":["mc14302","mc14373","mc86352","mc98746","mc43208","mc53794"]},"rnbq1rk1/pp4pp/2pbpn2/3p1p2/2PP4/1P3NP1/P3PPBP/RNBQ1RK1 w - -":{"w":1,"d":1,"b":0,"r":2600,"m":[{"san":"Ba3","uci":"c1a3","w":1,"d":1,"b":0,"r":2600}],"g":["mc14311","mc86998"]},"rnbqk2r/ppp2ppp/4pn2/8/1b1Pp1Q1/2N5/PPPB1PPP/R3KBNR w KQkq -":{"w":3,"d":0,"b":0,"r":2580,"m":[{"san":"Qxg7","uci":"g4g7","w":3,"d":0,"b":0,"r":2580}],"g":["mc14478","mc53635","mc47301"]},"rnb1kb1r/pp3pp1/1q2pn1p/2pp4/3PP2B/P1N2P2/1PP1N1PP/R2QKB1R b KQkq -":{"w":2,"d":0,"b":0,"r":2700,"m":[{"san":"Nc6","uci":"b8c6","w":2,"d":0,"b":0,"r":2700}],"g":["mc14686","mc96943"]},"r1bqk2r/pp1pnpbp/2n3p1/2p1p3/2P5/2NP1NP1/PP2PPBP/R1BQ1RK1 b kq -":{"w":3,"d":2,"b":2,"r":2631,"m":[{"san":"O-O","uci":"e8g8","w":1,"d":2,"b":2,"r":2585},{"san":"d6","uci":"d7d6","w":2,"d":0,"b":0,"r":2746}],"g":["mc30506","mc89375","mc42134","mc14839","mc47944","mc63527","mc91581"]},"rnbqkbnr/pp2pppp/2p5/3pP3/8/8/PPPPNPPP/RNBQKB1R b KQkq -":{"w":3,"d":0,"b":3,"r":2576,"m":[{"san":"c5","uci":"c6c5","w":2,"d":0,"b":3,"r":2560},{"san":"Bf5","uci":"c8f5","w":1,"d":0,"b":0,"r":2653}],"g":["mc22480","mc14868","mc15627","mc86724","mc15694","mc15823"]},"r1bqkb1r/p2npp1p/2pp1np1/1p6/3PP3/2N1BP1N/PPPQ2PP/R3KB1R b KQkq -":{"w":0,"d":0,"b":2,"r":2600,"m":[{"san":"Bb7","uci":"c8b7","w":0,"d":0,"b":1,"r":2600},{"san":"Nb6","uci":"d7b6","w":0,"d":0,"b":1,"r":2600}],"g":["mc14901","mc97572"]},"rn1qkb1r/pp2pp1p/2p2pb1/8/3P1B2/3B1N2/PPP2PPP/R2QK2R b KQkq -":{"w":1,"d":1,"b":0,"r":2500,"m":[{"san":"e6","uci":"e7e6","w":1,"d":1,"b":0,"r":2500}],"g":["mc14999","mc16041"]},"rnbqk2r/ppp1ppbp/3p1np1/8/2PP1B2/2N2N2/PP2PPPP/R2QKB1R b KQkq -":{"w":5,"d":3,"b":1,"r":2551,"m":[{"san":"Nbd7","uci":"b8d7","w":2,"d":1,"b":1,"r":2550},{"san":"Nh5","uci":"f6h5","w":3,"d":0,"b":0,"r":2567},{"san":"O-O","uci":"e8g8","w":0,"d":2,"b":0,"r":2532}],"g":["mc53644","mc53796","mc86154","mc86326","mc16418","mc15024","mc15045","mc15077","mc54206"]},"rnbqkbnr/pp1ppp1p/2p3p1/8/3PP3/5N2/PPP2PPP/RNBQKB1R b KQkq -":{"w":4,"d":2,"b":7,"r":2621,"m":[{"san":"d5","uci":"d7d5","w":4,"d":0,"b":7,"r":2623},{"san":"Bg7","uci":"f8g7","w":0,"d":2,"b":0,"r":2608}],"g":["mc80897","mc70787","mc81053","mc80828","mc80037","mc81028","mc80279","mc80387","mc80282","mc80872"]},"rnbqk2r/pp2bppp/4pn2/8/2BP4/P1N2N2/1P3PPP/R1BQK2R b KQkq -":{"w":0,"d":2,"b":0,"r":2565,"m":[{"san":"O-O","uci":"e8g8","w":0,"d":2,"b":0,"r":2565}],"g":["mc108117","mc15133"]},"rnbqk1nr/pppp1ppp/4p3/8/2P5/P1P5/1P2PPPP/R1BQKBNR b KQkq -":{"w":0,"d":1,"b":1,"r":2500,"m":[{"san":"d6","uci":"d7d6","w":0,"d":0,"b":1,"r":2500},{"san":"Nf6","uci":"g8f6","w":0,"d":1,"b":0,"r":2500}],"g":["mc15184","mc15951"]},"rnbq1rk1/ppppnppp/4p3/8/1bP5/2N2NP1/PP1PPPBP/R1BQK2R b KQ -":{"w":0,"d":2,"b":0,"r":2475,"m":[{"san":"Bxc3","uci":"b4c3","w":0,"d":1,"b":0,"r":2500},{"san":"d5","uci":"d7d5","w":0,"d":1,"b":0,"r":2450}],"g":["mc15498","mc16652"]},"r1q1kb1r/pp3ppp/2nppn2/2p5/3PP1b1/2P2N2/PPQ1BPPP/RNBR2K1 b kq -":{"w":0,"d":2,"b":0,"r":2600,"m":[{"san":"Be7","uci":"f8e7","w":0,"d":2,"b":0,"r":2600}],"g":["mc15684","mc97096"]},"r1bqkbnr/pppp2pp/2n5/5pB1/2PPp3/2N2N2/PP2PPPP/R2QKB1R b KQkq -":{"w":2,"d":0,"b":1,"r":2494,"m":[{"san":"Be7","uci":"f8e7","w":1,"d":0,"b":1,"r":2508},{"san":"Nf6","uci":"g8f6","w":1,"d":0,"b":0,"r":2468}],"g":["mc100019","mc15786","mc16433"]},"rnbq1rk1/pp2bppp/4pn2/3P2B1/3P4/2N5/PP3PPP/R2QKBNR w KQ -":{"w":0,"d":2,"b":0,"r":2475,"m":[{"san":"Bd3","uci":"f1d3","w":0,"d":2,"b":0,"r":2475}],"g":["mc16632","mc98540"]},"rnbqk2r/pp1p1ppp/4pn2/2p5/2PP4/P4N2/1P1QPPPP/RN2KB1R b KQkq -":{"w":1,"d":4,"b":0,"r":2605,"m":[{"san":"cxd4","uci":"c5d4","w":1,"d":2,"b":0,"r":2525},{"san":"b6","uci":"b7b6","w":0,"d":2,"b":0,"r":2726}],"g":["mc81581","mc81554","mc57263","mc58869","mc16699"]},"r1bqk2r/pp2bppp/2n1pn2/2p5/2BP4/2N1PN2/PP3PPP/R1BQ1RK1 b kq -":{"w":0,"d":1,"b":1,"r":2600,"m":[{"san":"O-O","uci":"e8g8","w":0,"d":1,"b":1,"r":2600}],"g":["mc16789","mc16797"]},"r1bqk1nr/pp2ppbp/2np2p1/8/2PNP3/2N1B3/PP3PPP/R2QKB1R b KQkq -":{"w":6,"d":3,"b":2,"r":2574,"m":[{"san":"Nh6","uci":"g8h6","w":3,"d":3,"b":1,"r":2534},{"san":"Nf6","uci":"g8f6","w":3,"d":0,"b":1,"r":2645}],"g":["mc18517","mc56759","mc108365","mc16954","mc65536","mc51235","mc24266","mc64000","mc63386","mc63626"]},"rnbq1rk1/ppp2ppp/3b4/5p2/2BP4/2N1PN2/PP3PPP/R2QK2R b KQ -":{"w":0,"d":1,"b":2,"r":2661,"m":[{"san":"Nd7","uci":"b8d7","w":0,"d":1,"b":2,"r":2661}],"g":["mc67664","mc52828","mc17636"]},"r1bqk2r/1pp2ppp/2nppn2/p7/2PP4/P1B2N2/1PQ1PPPP/R3KB1R b KQkq -":{"w":0,"d":2,"b":2,"r":2657,"m":[{"san":"Qe7","uci":"d8e7","w":0,"d":2,"b":2,"r":2657}],"g":["mc18113","mc45568","mc24552","mc90699"]},"rnbqk1nr/pp3pbp/3p2p1/2p1p3/2P1P3/2NP2P1/PP2NP1P/R1BQKB1R b KQkq -":{"w":0,"d":2,"b":0,"r":2821,"m":[{"san":"Nc6","uci":"b8c6","w":0,"d":2,"b":0,"r":2821}],"g":["mc18578","mc24792"]},"rnbq1rk1/1p2ppbp/5np1/p1Pp4/8/2P1BNP1/PP2PPBP/RN1Q1RK1 b - -":{"w":2,"d":0,"b":0,"r":2832,"m":[{"san":"Nc6","uci":"b8c6","w":2,"d":0,"b":0,"r":2832}],"g":["mc18702","mc24974"]},"rnbqkb1r/ppp2ppp/5n2/3pp3/8/3P1NP1/PPP1PPBP/RNBQK2R b KQkq -":{"w":14,"d":6,"b":6,"r":2700,"m":[{"san":"Bd6","uci":"f8d6","w":7,"d":3,"b":3,"r":2722},{"san":"Nc6","uci":"b8c6","w":7,"d":2,"b":3,"r":2678},{"san":"Nbd7","uci":"b8d7","w":0,"d":1,"b":0,"r":2676}],"g":["mc40033","mc70403","mc61199","mc103691","mc78264","mc60903","mc74220","mc39080","mc19017","mc19035"]},"r2qk1nr/pp1n1ppp/2pbp3/3p4/6b1/3P1NPP/PPPNPPB1/R1BQ1RK1 b kq -":{"w":0,"d":1,"b":1,"r":2666,"m":[{"san":"Bh5","uci":"g4h5","w":0,"d":1,"b":1,"r":2666}],"g":["mc19026","mc97500"]},"r2qkb1r/ppp2ppp/2n1p3/3n3b/3P4/2P2N1P/PP2BPP1/RNBQ1RK1 b kq -":{"w":1,"d":1,"b":0,"r":2683,"m":[{"san":"Be7","uci":"f8e7","w":1,"d":1,"b":0,"r":2683}],"g":["mc19168","mc85500"]},"rn1qk2r/ppp2ppp/3bbn2/3p4/2PP4/3B1N2/PP2QPPP/RNB1K2R b KQkq -":{"w":0,"d":0,"b":2,"r":2791,"m":[{"san":"dxc4","uci":"d5c4","w":0,"d":0,"b":2,"r":2791}],"g":["mc19390","mc39990"]},"r1bqkbnr/1p1ppppp/p7/2p5/3nP3/2NB1N2/PPPP1PPP/R1BQK2R b KQkq -":{"w":2,"d":4,"b":1,"r":2695,"m":[{"san":"Nc6","uci":"d4c6","w":1,"d":4,"b":1,"r":2720},{"san":"g6","uci":"g7g6","w":1,"d":0,"b":0,"r":2542}],"g":["mc19618","mc21045","mc39546","mc19500","mc42831","mc42772","mc42875"]},"r1bqk1nr/pp1p1ppp/2n1p3/2b5/2P1P3/8/PPN2PPP/RNBQKB1R b KQkq -":{"w":2,"d":0,"b":0,"r":2834,"m":[{"san":"Nf6","uci":"g8f6","w":2,"d":0,"b":0,"r":2834}],"g":["mc19595","mc25919"]},"rnbqkb1r/ppp2p2/3ppn1p/6p1/3P4/2P2NB1/PP2PPPP/RN1QKB1R b KQkq -":{"w":1,"d":1,"b":0,"r":2687,"m":[{"san":"Nh5","uci":"f6h5","w":1,"d":0,"b":0,"r":2767},{"san":"Ne4","uci":"f6e4","w":0,"d":1,"b":0,"r":2606}],"g":["mc19630","mc60730"]},"rnb1kb1r/pp2pppp/1q3n2/3p2B1/3P4/5N2/PPPN1PPP/R2QKB1R b KQkq -":{"w":2,"d":1,"b":0,"r":2775,"m":[{"san":"Nc6","uci":"b8c6","w":2,"d":1,"b":0,"r":2775}],"g":["mc19687","mc81505","mc34585"]},"r1bqkbnr/pp3p2/2np2pp/2p1p2P/2B1P3/2NP1N2/PPP2PP1/R1BQK2R b KQkq -":{"w":0,"d":0,"b":2,"r":2825,"m":[{"san":"g5","uci":"g6g5","w":0,"d":0,"b":2,"r":2825}],"g":["mc19726","mc83494"]},"r1b1k1nr/pp2qpbp/2p3p1/2p1p3/P3P3/3P1N2/1PP2PPP/RNBQR1K1 b kq -":{"w":3,"d":5,"b":4,"r":2765,"m":[{"san":"Nf6","uci":"g8f6","w":3,"d":5,"b":4,"r":2765}],"g":["mc23921","mc29195","mc23341","mc23345","mc85627","mc85630","mc19892","mc21502","mc85571","mc84856"]},"r1bqk2r/3pnppp/p1nb4/1pp1p3/4P3/2PP1N2/PPB2PPP/RNBQ1RK1 b kq -":{"w":4,"d":2,"b":0,"r":2836,"m":[{"san":"Ng6","uci":"e7g6","w":2,"d":2,"b":0,"r":2829},{"san":"O-O","uci":"e8g8","w":2,"d":0,"b":0,"r":2849}],"g":["mc20074","mc20075","mc26354","mc26355","mc21997","mc27750"]},"r1bqk1nr/ppp1ppbp/2np2p1/8/3PP3/5N2/PPP1BPPP/RNBQ1RK1 b kq -":{"w":0,"d":2,"b":0,"r":2824,"m":[{"san":"e5","uci":"e7e5","w":0,"d":2,"b":0,"r":2824}],"g":["mc20165","mc83915"]},"r2qk2r/pppn1ppp/2p1b3/2b1p3/4P3/3P1N1P/PPP2PP1/R1BQKN1R b KQkq -":{"w":0,"d":2,"b":0,"r":2800,"m":[{"san":"f6","uci":"f7f6","w":0,"d":2,"b":0,"r":2800}],"g":["mc20215","mc76377"]},"rnbq1rk1/pppp1ppp/4pn2/8/1bPP4/1QN2N2/PP2PPPP/R1B1KB1R b KQ -":{"w":1,"d":4,"b":0,"r":2680,"m":[{"san":"c5","uci":"c7c5","w":1,"d":4,"b":0,"r":2680}],"g":["mc20515","mc46892","mc72548","mc32861","mc57174"]},"rnbqkbnr/ppp2ppp/4p3/8/4N3/5N2/PPPP1PPP/R1BQKB1R b KQkq -":{"w":1,"d":1,"b":2,"r":2632,"m":[{"san":"Nd7","uci":"b8d7","w":1,"d":1,"b":2,"r":2632}],"g":["mc20607","mc20633","mc81768","mc81772"]},"r1bqk2r/pppp1ppp/2n1pn2/8/2PP4/P1b2P2/1P2P1PP/R1BQKBNR w KQkq -":{"w":0,"d":1,"b":1,"r":2656,"m":[{"san":"bxc3","uci":"b2c3","w":0,"d":1,"b":1,"r":2656}],"g":["mc20713","mc87994"]},"rnb1k2r/pp1pppbp/6p1/q1p5/2PP4/2N2NP1/PP1QPPBP/R3K2R b KQkq -":{"w":4,"d":2,"b":0,"r":2733,"m":[{"san":"d6","uci":"d7d6","w":2,"d":1,"b":0,"r":2783},{"san":"cxd4","uci":"c5d4","w":1,"d":1,"b":0,"r":2669},{"san":"O-O","uci":"e8g8","w":1,"d":0,"b":0,"r":2708}],"g":["mc20929","mc30814","mc49744","mc50092","mc48945","mc92279"]},"rnbqkb1r/pp1ppp1p/6p1/4P3/3p3P/P7/1PP1NPP1/RNBQK2R w KQkq -":{"w":2,"d":0,"b":0,"r":2809,"m":[{"san":"h5","uci":"h4h5","w":2,"d":0,"b":0,"r":2809}],"g":["mc21037","mc71713"]},"rnbqk2r/pp1pppbp/5np1/8/2Pp4/2N1PN2/PP3PPP/R1BQKB1R w KQkq -":{"w":2,"d":2,"b":2,"r":2630,"m":[{"san":"Nxd4","uci":"f3d4","w":2,"d":1,"b":1,"r":2632},{"san":"exd4","uci":"e3d4","w":0,"d":1,"b":1,"r":2627}],"g":["mc30625","mc76272","mc21133","mc55065","mc55289","mc55345"]},"rnb1k2r/ppp1qppp/3p1n2/8/2Pp4/4PN2/PP3PPP/R1BQKB1R w KQkq -":{"w":0,"d":0,"b":2,"r":2818,"m":[{"san":"Nxd4","uci":"f3d4","w":0,"d":0,"b":2,"r":2818}],"g":["mc21212","mc71956"]},"rnbqk1nr/ppp1ppbp/6p1/3p4/4PP2/3P1N2/PPP3PP/RNBQKB1R b KQkq -":{"w":3,"d":0,"b":0,"r":2649,"m":[{"san":"dxe4","uci":"d5e4","w":2,"d":0,"b":0,"r":2585},{"san":"c5","uci":"c7c5","w":1,"d":0,"b":0,"r":2778}],"g":["mc21239","mc21817","mc64131"]},"rnbqkbnr/ppp2pp1/8/3pp1Pp/8/3P3P/PPP1PP2/RNBQKBNR b KQkq -":{"w":0,"d":1,"b":1,"r":2712,"m":[{"san":"Nc6","uci":"b8c6","w":0,"d":1,"b":0,"r":2793},{"san":"Ne7","uci":"g8e7","w":0,"d":0,"b":1,"r":2630}],"g":["mc21410","mc80601"]},"r1bqk2r/pp2nppp/2n1p3/2pp4/P1PP4/2P1PN2/5PPP/R1BQKB1R b KQkq -":{"w":2,"d":0,"b":0,"r":2809,"m":[{"san":"O-O","uci":"e8g8","w":2,"d":0,"b":0,"r":2809}],"g":["mc21820","mc27581"]},"r1bq1rk1/ppp1bppp/2n1pn2/8/2pPP3/2N2NP1/PP3PBP/R1BQ1RK1 b - -":{"w":2,"d":2,"b":2,"r":2734,"m":[{"san":"a6","uci":"a7a6","w":0,"d":2,"b":1,"r":2707},{"san":"Rb8","uci":"a8b8","w":2,"d":0,"b":1,"r":2761}],"g":["mc21895","mc36451","mc21976","mc84826","mc27790","mc53908"]},"rnbqk2r/ppp1ppbp/3p1np1/8/4PP2/1P3N2/PBPP2PP/RN1QKB1R b KQkq -":{"w":0,"d":0,"b":3,"r":2751,"m":[{"san":"O-O","uci":"e8g8","w":0,"d":0,"b":3,"r":2751}],"g":["mc21985","mc84835","mc33739"]},"r1bqkb1r/pp2nppp/2n1p3/1B1pP3/3P4/5N2/PP3PPP/RNBQK2R b KQkq -":{"w":0,"d":1,"b":2,"r":2773,"m":[{"san":"Bd7","uci":"c8d7","w":0,"d":1,"b":2,"r":2773}],"g":["mc22255","mc27868","mc88438"]},"rn1qkbnr/1p3ppp/p3p3/2ppP3/2PP4/3Q1N2/PP3PPP/RNB2RK1 b kq -":{"w":0,"d":0,"b":2,"r":2745,"m":[{"san":"Nc6","uci":"b8c6","w":0,"d":0,"b":2,"r":2745}],"g":["mc22607","mc95778"]},"r1bqk2r/ppp2pp1/2np1n1p/2b1p3/N1B1P3/3P1N2/PPP2PPP/R1BQ1RK1 b kq -":{"w":3,"d":3,"b":1,"r":2726,"m":[{"san":"Bb6","uci":"c5b6","w":2,"d":3,"b":1,"r":2737},{"san":"a6","uci":"a7a6","w":1,"d":0,"b":0,"r":2661}],"g":["mc22669","mc81572","mc42106","mc62428","mc78071","mc37131","mc51195"]},"rnbqkb1r/pp2pp1p/5np1/1Bpp4/8/1P2PN2/PBPP1PPP/RN1QK2R b KQkq -":{"w":4,"d":4,"b":1,"r":2714,"m":[{"san":"Bd7","uci":"c8d7","w":4,"d":4,"b":1,"r":2714}],"g":["mc23411","mc80915","mc23272","mc23968","mc61869","mc72146","mc81004","mc36664","mc63666"]},"r1bqk1nr/ppp2pbp/2np2p1/4p3/2P5/1PN1PN2/PB1P1PPP/R2QKB1R b KQkq -":{"w":2,"d":0,"b":0,"r":2818,"m":[{"san":"Nf6","uci":"g8f6","w":2,"d":0,"b":0,"r":2818}],"g":["mc23429","mc80929"]},"rnbqkb1r/pppp2pp/4pn2/5p2/2PP4/P1N5/1P2PPPP/R1BQKBNR b KQkq -":{"w":4,"d":0,"b":2,"r":2656,"m":[{"san":"g6","uci":"g7g6","w":2,"d":0,"b":2,"r":2643},{"san":"d6","uci":"d7d6","w":1,"d":0,"b":0,"r":2623},{"san":"Be7","uci":"f8e7","w":1,"d":0,"b":0,"r":2745}],"g":["mc110207","mc109776","mc47572","mc23983","mc70268","mc47877"]},"r2qkbnr/ppp1pppp/2n5/3p4/3P2b1/5NP1/PPP1PPBP/RNBQK2R b KQkq -":{"w":7,"d":2,"b":1,"r":2662,"m":[{"san":"Qd7","uci":"d8d7","w":5,"d":2,"b":1,"r":2640},{"san":"e6","uci":"e7e6","w":2,"d":0,"b":0,"r":2750}],"g":["mc83797","mc104586","mc40619","mc104596","mc89143","mc25011","mc109732","mc32551","mc58871","mc64830"]},"r1bqk2r/ppp2ppp/3p1n2/2b1p3/N1BnP3/3P1N2/PPP2PPP/R1BQK2R b KQkq -":{"w":3,"d":9,"b":2,"r":2728,"m":[{"san":"b5","uci":"b7b5","w":3,"d":7,"b":2,"r":2734},{"san":"Nxf3+","uci":"d4f3","w":0,"d":2,"b":0,"r":2690}],"g":["mc25695","mc103529","mc83654","mc76022","mc76034","mc83692","mc83704","mc34666","mc104267","mc84452"]},"rnbqk2r/ppp1bppp/8/3pP3/8/3B1N2/PPPB1PPP/R2QK2R b KQkq -":{"w":0,"d":0,"b":2,"r":2776,"m":[{"san":"c5","uci":"c7c5","w":0,"d":0,"b":2,"r":2776}],"g":["mc25737","mc40122"]},"rnbq1rk1/2p1ppBp/p2p1np1/1p6/3PP3/2N5/PPPQ1PPP/2KR1BNR b - -":{"w":0,"d":0,"b":2,"r":2797,"m":[{"san":"Kxg7","uci":"g8g7","w":0,"d":0,"b":2,"r":2797}],"g":["mc26089","mc83511"]},"r1bqkb1r/1p1npp1p/p2p1np1/8/3PP3/5N2/PPB2PPP/RNBQK2R b KQkq -":{"w":0,"d":2,"b":0,"r":2776,"m":[{"san":"Bg7","uci":"f8g7","w":0,"d":2,"b":0,"r":2776}],"g":["mc26462","mc104790"]},"rn1qk2r/pbp2ppp/1p1bpn2/3p4/2PP4/1P1BPN2/PB3PPP/RN1QK2R b KQkq -":{"w":1,"d":0,"b":3,"r":2682,"m":[{"san":"O-O","uci":"e8g8","w":1,"d":0,"b":1,"r":2581},{"san":"dxc4","uci":"d5c4","w":0,"d":0,"b":1,"r":2775},{"san":"Nbd7","uci":"b8d7","w":0,"d":0,"b":1,"r":2793}],"g":["mc81050","mc27659","mc27080","mc32436"]},"rnbq1rk1/pp2ppbp/3p1np1/2pP4/2P1P2P/2N5/PP2BPP1/R1BQK1NR b KQ -":{"w":7,"d":2,"b":0,"r":2716,"m":[{"san":"e6","uci":"e7e6","w":4,"d":2,"b":0,"r":2704},{"san":"b5","uci":"b7b5","w":3,"d":0,"b":0,"r":2739}],"g":["mc40382","mc27624","mc31021","mc105085","mc89337","mc40406","mc77692","mc35221","mc85863"]},"rn1qkb1r/pbpp2pp/1p2pn2/5p2/2PP1B2/P1N1P3/1P3PPP/R2QKBNR b KQkq -":{"w":4,"d":1,"b":0,"r":2688,"m":[{"san":"Be7","uci":"f8e7","w":2,"d":1,"b":0,"r":2683},{"san":"g6","uci":"g7g6","w":1,"d":0,"b":0,"r":2719},{"san":"d6","uci":"d7d6","w":1,"d":0,"b":0,"r":2673}],"g":["mc40471","mc41333","mc27710","mc81323","mc42054"]},"r1bqkb1r/1p2ppp1/p1n2n1p/2Pp4/5B2/2NBP3/PPP2PPP/R2QK1NR w KQkq -":{"w":1,"d":1,"b":0,"r":2671,"m":[{"san":"Bg3","uci":"f4g3","w":1,"d":0,"b":0,"r":2636},{"san":"Nf3","uci":"g1f3","w":0,"d":1,"b":0,"r":2705}],"g":["mc80307","mc28981"]},"r1bqk2r/pppp1pbp/2n2np1/4p3/1PP5/P2P1N2/1B2PPPP/RN1QKB1R b KQkq -":{"w":0,"d":1,"b":1,"r":2728,"m":[{"san":"d6","uci":"d7d6","w":0,"d":1,"b":1,"r":2728}],"g":["mc110267","mc29242"]},"rnbqk2r/pp2ppbp/5np1/3p4/2PP4/2N2N1P/PP3PP1/R1BQKB1R b KQkq -":{"w":2,"d":0,"b":0,"r":2668,"m":[{"san":"O-O","uci":"e8g8","w":2,"d":0,"b":0,"r":2668}],"g":["mc79844","mc29278"]},"r1bq1rk1/pppnbppp/4p3/2Pp3n/3P1B2/2N1PN2/PP2BPPP/R2QK2R b KQ -":{"w":0,"d":13,"b":0,"r":2753,"m":[{"san":"Nxf4","uci":"h5f4","w":0,"d":10,"b":0,"r":2747},{"san":"b6","uci":"b7b6","w":0,"d":2,"b":0,"r":2786},{"san":"c6","uci":"c7c6","w":0,"d":1,"b":0,"r":2740}],"g":["mc39419","mc74439","mc39124","mc89077","mc40169","mc85256","mc76207","mc74051","mc76157","mc89652"]},"rn1qkb1r/pb1ppppp/5n2/2pP4/2p5/5NP1/PP2PPBP/RNBQK2R w KQkq -":{"w":1,"d":1,"b":0,"r":2687,"m":[{"san":"Nc3","uci":"b1c3","w":1,"d":1,"b":0,"r":2687}],"g":["mc40840","mc29608"]},"rn1qkb1r/p2p1p1p/bp3np1/2pP4/8/2N2NP1/PPQ1PP1P/R1B1KB1R b KQkq -":{"w":1,"d":1,"b":0,"r":2631,"m":[{"san":"Bg7","uci":"f8g7","w":1,"d":1,"b":0,"r":2631}],"g":["mc46974","mc29610"]},"rnbq1rk1/pp2ppbp/3p1np1/2pP4/2P5/2N3PN/PP2PPBP/R1BQK2R b KQ -":{"w":2,"d":1,"b":1,"r":2690,"m":[{"san":"a6","uci":"a7a6","w":2,"d":1,"b":1,"r":2690}],"g":["mc29881","mc104059","mc51089","mc51099"]},"rnbq1rk1/1p2ppbp/p2p1np1/2pP4/P1P5/2N3PN/1P2PPBP/R1BQK2R b KQ -":{"w":2,"d":1,"b":1,"r":2690,"m":[{"san":"e6","uci":"e7e6","w":2,"d":0,"b":1,"r":2722},{"san":"b5","uci":"b7b5","w":0,"d":1,"b":0,"r":2595}],"g":["mc29881","mc104059","mc51089","mc51099"]},"r1bqkb1r/1p3ppp/p1n1pn2/2p5/3P4/P1N1PN2/BP3PPP/R1BQK2R b KQkq -":{"w":2,"d":1,"b":0,"r":2773,"m":[{"san":"b5","uci":"b7b5","w":2,"d":1,"b":0,"r":2773}],"g":["mc84588","mc31217","mc84663"]},"rn1qkb1r/pp3ppp/2p2n2/3p4/3P4/2NQPN2/PP3PPP/R1B1K2R b KQkq -":{"w":2,"d":0,"b":0,"r":2600,"m":[{"san":"Bd6","uci":"f8d6","w":2,"d":0,"b":0,"r":2600}],"g":["mc31958","mc65854"]},"r1bqk2r/2p1ppbp/p1pp1np1/4P3/3P4/2N2N2/PPP2PPP/R1BQ1RK1 b kq -":{"w":1,"d":1,"b":0,"r":2562,"m":[{"san":"Nd7","uci":"f6d7","w":0,"d":1,"b":0,"r":2500},{"san":"Nd5","uci":"f6d5","w":1,"d":0,"b":0,"r":2623}],"g":["mc95191","mc32126"]},"rnbqkb1r/pp1ppp1p/5np1/3p4/2P5/6P1/PP2PP1P/RNBQKBNR w KQkq -":{"w":3,"d":2,"b":0,"r":2567,"m":[{"san":"cxd5","uci":"c4d5","w":3,"d":2,"b":0,"r":2567}],"g":["mc35679","mc55895","mc32346","mc32408","mc55768"]},"r1bq1rk1/ppp1ppbp/2np1np1/8/3P4/5NP1/PPPNPPBP/R1BQ1RK1 w - -":{"w":1,"d":4,"b":0,"r":2598,"m":[{"san":"e4","uci":"e2e4","w":1,"d":3,"b":0,"r":2598},{"san":"c3","uci":"c2c3","w":0,"d":1,"b":0,"r":2600}],"g":["mc49960","mc107207","mc32908","mc86274","mc64369"]},"rn1q1rk1/ppp1ppbp/3p1np1/8/3PPPb1/2NB1N1P/PPP3P1/R1BQK2R b KQ -":{"w":3,"d":0,"b":0,"r":2661,"m":[{"san":"Bxf3","uci":"g4f3","w":3,"d":0,"b":0,"r":2661}],"g":["mc84150","mc56072","mc32954"]},"r1bqk2r/pp1ppp1p/2n2np1/8/2P5/2P2P2/P1N1P1PP/R1BQKB1R b KQkq -":{"w":0,"d":1,"b":1,"r":2550,"m":[{"san":"d6","uci":"d7d6","w":0,"d":0,"b":1,"r":2600},{"san":"Qa5","uci":"d8a5","w":0,"d":1,"b":0,"r":2500}],"g":["mc33165","mc55630"]},"rnbqk2r/1p1p1ppp/p3p3/3nP3/1b1N4/2N5/PPP1BPPP/R1BQ1RK1 b kq -":{"w":1,"d":0,"b":1,"r":2669,"m":[{"san":"Nxc3","uci":"d5c3","w":1,"d":0,"b":1,"r":2669}],"g":["mc33699","mc103904"]},"r1bqk2r/p3ppbp/1pp3pn/2p5/4P3/2NPBN1P/PPP2PP1/R2QK2R b KQkq -":{"w":2,"d":2,"b":0,"r":2745,"m":[{"san":"f6","uci":"f7f6","w":2,"d":2,"b":0,"r":2745}],"g":["mc33821","mc89061","mc59784","mc101942"]},"rn1qkbnr/pbpp1ppp/1p2p3/8/8/1P2PN2/PBPP1PPP/RN1QKB1R b KQkq -":{"w":0,"d":0,"b":2,"r":2744,"m":[{"san":"Nf6","uci":"g8f6","w":0,"d":0,"b":2,"r":2744}],"g":["mc33887","mc46290"]},"rnb1kb1r/1pq2ppp/p2ppn2/8/2PNP3/2N5/PP2BPPP/R1BQ1RK1 b kq -":{"w":2,"d":0,"b":0,"r":2590,"m":[{"san":"Be7","uci":"f8e7","w":1,"d":0,"b":0,"r":2621},{"san":"b6","uci":"b7b6","w":1,"d":0,"b":0,"r":2558}],"g":["mc35213","mc66300"]},"r2qk1nr/1bpnppbp/p2p2p1/1p6/P2PP3/2NBBN2/1PP2PPP/R2Q1RK1 b kq -":{"w":1,"d":0,"b":1,"r":2709,"m":[{"san":"b4","uci":"b5b4","w":1,"d":0,"b":1,"r":2709}],"g":["mc35619","mc77990"]},"rnbq1rk1/ppp1ppbp/3p1np1/8/2PP4/1P2PN2/P3BPPP/RNBQK2R b KQ -":{"w":0,"d":2,"b":0,"r":2757,"m":[{"san":"a5","uci":"a7a5","w":0,"d":2,"b":0,"r":2757}],"g":["mc35786","mc77210"]},"r1bqkbnr/pp2p1pp/2n2p2/3p4/3N4/1P4P1/PBP1PP1P/RN1QKB1R b KQkq -":{"w":2,"d":0,"b":0,"r":2755,"m":[{"san":"e5","uci":"e7e5","w":2,"d":0,"b":0,"r":2755}],"g":["mc35863","mc77390"]},"rn2kb1r/pp1Q1ppp/4pn2/2pp4/3P4/P3PN2/1PP2PPP/RNB1K2R b KQkq -":{"w":0,"d":2,"b":0,"r":2755,"m":[{"san":"Nbxd7","uci":"b8d7","w":0,"d":2,"b":0,"r":2755}],"g":["mc35879","mc77405"]},"r1bqkb1r/p4ppp/2p2n2/3pp3/8/1P4P1/PBP1PPBP/RN1QK2R b KQkq -":{"w":0,"d":0,"b":2,"r":2755,"m":[{"san":"Bb4+","uci":"f8b4","w":0,"d":0,"b":2,"r":2755}],"g":["mc35884","mc77410"]},"r1b1kb1r/ppp2ppp/2nq4/4p3/8/P1P2NP1/2QPPP1P/R1B1KB1R b KQkq -":{"w":0,"d":2,"b":0,"r":2787,"m":[{"san":"Qg6","uci":"d6g6","w":0,"d":2,"b":0,"r":2787}],"g":["mc36336","mc84733"]},"r2qk2r/ppp2ppp/2pbbn2/4p1N1/4P3/2PP4/PP1N1PPP/R1BQK2R b KQkq -":{"w":2,"d":0,"b":0,"r":2766,"m":[{"san":"Bg4","uci":"e6g4","w":2,"d":0,"b":0,"r":2766}],"g":["mc36580","mc85004"]},"r1bqk2r/pp2bppp/2n1pn2/2p5/P3P3/5NP1/1PP1QPBP/RNB1K2R b KQkq -":{"w":0,"d":1,"b":1,"r":2673,"m":[{"san":"e5","uci":"e6e5","w":0,"d":1,"b":1,"r":2673}],"g":["mc36592","mc42945"]},"rnbqk2r/pp2ppbp/6p1/2pn4/7P/2N2NP1/PP1PPPB1/R1BQK2R b KQkq -":{"w":3,"d":2,"b":0,"r":2736,"m":[{"san":"Nc6","uci":"b8c6","w":3,"d":0,"b":0,"r":2726},{"san":"h6","uci":"h7h6","w":0,"d":2,"b":0,"r":2750}],"g":["mc40856","mc104841","mc36703","mc82227","mc105385"]},"r1bqkbnr/ppp1pppp/1n6/3p4/3P4/5NP1/PPPNPP1P/R1BQKB1R b KQkq -":{"w":1,"d":2,"b":0,"r":2701,"m":[{"san":"Nf6","uci":"g8f6","w":0,"d":2,"b":0,"r":2716},{"san":"Bf5","uci":"c8f5","w":1,"d":0,"b":0,"r":2673}],"g":["mc37308","mc37264","mc37235"]},"rnbqk1nr/ppp1ppbp/3p2p1/8/2B1P3/5N2/PPPP1PPP/RNBQ1RK1 b kq -":{"w":1,"d":0,"b":1,"r":2633,"m":[{"san":"Nf6","uci":"g8f6","w":0,"d":0,"b":1,"r":2500},{"san":"e6","uci":"e7e6","w":1,"d":0,"b":0,"r":2765}],"g":["mc84670","mc37500"]},"r1b1kb1r/pp1n1ppp/2p1pn2/q2p2B1/2PP4/4PN2/PPQN1PPP/R3KB1R b KQkq -":{"w":0,"d":3,"b":0,"r":2511,"m":[{"san":"Ne4","uci":"f6e4","w":0,"d":3,"b":0,"r":2511}],"g":["mc37587","mc37588","mc57288"]},"rn2kbnr/1p1b1ppp/1q2p3/p1ppP3/3P4/P1P2N2/1P2BPPP/RNBQK2R b KQkq -":{"w":3,"d":2,"b":2,"r":2595,"m":[{"san":"a4","uci":"a5a4","w":2,"d":1,"b":1,"r":2676},{"san":"Nc6","uci":"b8c6","w":1,"d":1,"b":1,"r":2487}],"g":["mc37714","mc37719","mc37720","mc93192","mc81755","mc81740","mc81647"]},"rnbqkb1r/pp2pp1p/6p1/3n4/2BP4/2N5/PP3PPP/R1BQK1NR b KQkq -":{"w":0,"d":1,"b":2,"r":2633,"m":[{"san":"Nb6","uci":"d5b6","w":0,"d":1,"b":2,"r":2633}],"g":["mc38521","mc38259","mc63667"]},"rnbqk2r/pppp1pp1/5n1p/4p3/2P1P3/2b3P1/PP1P1PBP/R1BQK1NR w KQkq -":{"w":0,"d":0,"b":2,"r":2712,"m":[{"san":"bxc3","uci":"b2c3","w":0,"d":0,"b":2,"r":2712}],"g":["mc38813","mc104480"]},"rnbqk1nr/ppp1p1bp/3p2p1/5pB1/2PP4/4PN2/PP3PPP/RN1QKB1R b KQkq -":{"w":2,"d":0,"b":0,"r":2761,"m":[{"san":"h6","uci":"h7h6","w":2,"d":0,"b":0,"r":2761}],"g":["mc38849","mc109531"]},"rnbqk2r/pp2ppbp/2p3p1/3n4/P1pP1B1P/2N2N2/1P2PPP1/R2QKB1R w KQkq -":{"w":2,"d":0,"b":0,"r":2770,"m":[{"san":"Be5","uci":"f4e5","w":2,"d":0,"b":0,"r":2770}],"g":["mc39292","mc69704"]},"r1bqkb1r/1p1npp1p/p2p1np1/6B1/3NP3/2N5/PPP1QPPP/2KR1B1R b kq -":{"w":1,"d":2,"b":0,"r":2743,"m":[{"san":"Bg7","uci":"f8g7","w":1,"d":2,"b":0,"r":2743}],"g":["mc74247","mc39399","mc74316"]},"rnb1kb1r/pp2pppp/2p2n2/q7/3P4/2N2N1P/PPP2PP1/R1BQKB1R b KQkq -":{"w":0,"d":1,"b":2,"r":2657,"m":[{"san":"Bf5","uci":"c8f5","w":0,"d":1,"b":2,"r":2657}],"g":["mc82760","mc40509","mc72852"]},"rn1q1rk1/pbppppbp/1p3np1/8/2PP4/1PN1PN2/PB3PPP/R2QKB1R b KQ -":{"w":1,"d":0,"b":1,"r":2771,"m":[{"san":"e6","uci":"e7e6","w":1,"d":0,"b":1,"r":2771}],"g":["mc74842","mc41313"]},"rn1qkb1r/p1pp1ppp/1p2pn2/8/2PP4/3B1PP1/PP3P1P/RNBQK2R b KQkq -":{"w":2,"d":0,"b":0,"r":2662,"m":[{"san":"Bb4+","uci":"f8b4","w":2,"d":0,"b":0,"r":2662}],"g":["mc42072","mc42118"]},"rnbq1rk1/pp3ppp/4pn2/2pp2B1/1bPP4/2N1PN2/PPQ2PPP/R3KB1R b KQ -":{"w":0,"d":3,"b":2,"r":2733,"m":[{"san":"cxd4","uci":"c5d4","w":0,"d":3,"b":0,"r":2726},{"san":"h6","uci":"h7h6","w":0,"d":0,"b":2,"r":2744}],"g":["mc67731","mc69716","mc42105","mc72495","mc69676"]},"r1bqk2r/pp3pbp/2nppnp1/2p5/4P3/2PP1NP1/PP3PBP/RNBQR1K1 b kq -":{"w":1,"d":0,"b":1,"r":2704,"m":[{"san":"e5","uci":"e6e5","w":0,"d":0,"b":1,"r":2674},{"san":"O-O","uci":"e8g8","w":1,"d":0,"b":0,"r":2733}],"g":["mc75780","mc42808"]},"rnbq1rk1/pp1p1ppp/5n2/2pP2B1/1b6/2N2N2/PP2PPPP/R2QKB1R b KQ -":{"w":0,"d":2,"b":0,"r":2678,"m":[{"san":"d6","uci":"d7d6","w":0,"d":2,"b":0,"r":2678}],"g":["mc67765","mc42813"]},"r1bq1rk1/pppnbppp/4pn2/3p4/2PP1B2/1QN1PN2/PP3PPP/R3KB1R b KQ -":{"w":2,"d":0,"b":0,"r":2729,"m":[{"san":"c6","uci":"c7c6","w":2,"d":0,"b":0,"r":2729}],"g":["mc45240","mc50717"]},"rnbqk2r/ppp1bppp/4pn2/3pP3/2PP4/P7/1P1N1PPP/R1BQKBNR b KQkq -":{"w":0,"d":2,"b":0,"r":2759,"m":[{"san":"Nfd7","uci":"f6d7","w":0,"d":2,"b":0,"r":2759}],"g":["mc46002","mc74041"]},"rn1qkbnr/pb1ppp1p/1p4p1/2p5/2PP4/5NP1/PP2PPBP/RNBQK2R b KQkq -":{"w":0,"d":4,"b":2,"r":2609,"m":[{"san":"cxd4","uci":"c5d4","w":0,"d":4,"b":2,"r":2609}],"g":["mc108665","mc47090","mc56564","mc56690","mc73755","mc91580"]},"r1bqkb1r/pp3ppp/2n2n2/3p2B1/3p4/P1N2N2/1P2PPPP/R2QKB1R w KQkq -":{"w":0,"d":2,"b":0,"r":2620,"m":[{"san":"Nxd4","uci":"f3d4","w":0,"d":2,"b":0,"r":2620}],"g":["mc71256","mc47815"]},"rn2k2r/pbppqppp/1p2pn2/8/2PP4/P1Q1PN2/1P3PPP/R1B1KB1R b KQkq -":{"w":2,"d":1,"b":0,"r":2680,"m":[{"san":"O-O","uci":"e8g8","w":1,"d":1,"b":0,"r":2689},{"san":"d6","uci":"d7d6","w":1,"d":0,"b":0,"r":2663}],"g":["mc49729","mc50212","mc49393"]},"r1b1kb1r/ppq2ppp/2n1pn2/2p5/2BP4/2N1PN2/PP2QPPP/R1B2RK1 b kq -":{"w":1,"d":2,"b":0,"r":2659,"m":[{"san":"a6","uci":"a7a6","w":1,"d":2,"b":0,"r":2659}],"g":["mc49997","mc108583","mc58094"]},"rnbqk2r/pp3ppp/4pn2/3p4/1bPp4/2N2NP1/PP2PPBP/R1BQK2R w KQkq -":{"w":2,"d":0,"b":0,"r":2705,"m":[{"san":"Nxd4","uci":"f3d4","w":2,"d":0,"b":0,"r":2705}],"g":["mc50171","mc108593"]},"rn2k2r/pp1q1ppp/3bpn2/2pP4/2P2P2/8/PP1PQ1PP/RNB1K1NR w KQkq -":{"w":1,"d":3,"b":0,"r":2597,"m":[{"san":"d3","uci":"d2d3","w":1,"d":1,"b":0,"r":2613},{"san":"dxe6","uci":"d5e6","w":0,"d":2,"b":0,"r":2580}],"g":["mc51916","mc91994","mc107048","mc64801"]},"rnbqkbnr/ppp3pp/4p3/3p1p2/2PP4/2N2N2/PP2PPPP/R1BQKB1R b KQkq -":{"w":1,"d":1,"b":0,"r":2594,"m":[{"san":"Nf6","uci":"g8f6","w":1,"d":1,"b":0,"r":2594}],"g":["mc51930","mc58100"]},"rnbqk2r/pp1pbppp/4p3/2pnP3/8/1P3NP1/PBPP1P1P/RN1QKB1R b KQkq -":{"w":1,"d":1,"b":0,"r":2584,"m":[{"san":"O-O","uci":"e8g8","w":1,"d":0,"b":0,"r":2658},{"san":"Nc6","uci":"b8c6","w":0,"d":1,"b":0,"r":2510}],"g":["mc52563","mc91475"]},"rnbqk2r/pppp2pp/4pn2/5p2/1bPP4/2NBP3/PP3PPP/R1BQK1NR b KQkq -":{"w":4,"d":2,"b":1,"r":2500,"m":[{"san":"Bxc3+","uci":"b4c3","w":1,"d":1,"b":0,"r":2500},{"san":"O-O","uci":"e8g8","w":2,"d":0,"b":0,"r":2500},{"san":"b6","uci":"b7b6","w":1,"d":0,"b":1,"r":2500},{"san":"Nc6","uci":"b8c6","w":0,"d":1,"b":0,"r":2500}],"g":["mc54273","mc54303","mc62900","mc101237","mc101247","mc101375","mc101379"]},"rn1qkb1r/ppp1p1pp/5n2/3p1bB1/3Pp3/2N2P2/PPP3PP/R2QKBNR w KQkq -":{"w":0,"d":0,"b":2,"r":2500,"m":[{"san":"fxe4","uci":"f3e4","w":0,"d":0,"b":2,"r":2500}],"g":["mc54768","mc64761"]},"r2qkbnr/ppp2ppp/2n5/4P3/2Pp2b1/5NP1/PP2PP1P/RNBQKB1R w KQkq -":{"w":2,"d":0,"b":0,"r":2550,"m":[{"san":"Bg2","uci":"f1g2","w":2,"d":0,"b":0,"r":2550}],"g":["mc99235","mc55566"]},"rnbqk2r/pp2ppbp/2p3p1/3p1n2/3P4/2P2NP1/PP1NPPBP/R1BQ1RK1 b kq -":{"w":0,"d":2,"b":0,"r":2612,"m":[{"san":"Nd6","uci":"f5d6","w":0,"d":2,"b":0,"r":2612}],"g":["mc109912","mc55568"]},"rnbqkb1r/1p1ppp1p/2p2np1/p7/1P6/P4NP1/1BPPPP1P/RN1QKB1R b KQkq -":{"w":0,"d":2,"b":0,"r":2500,"m":[{"san":"axb4","uci":"a5b4","w":0,"d":1,"b":0,"r":2500},{"san":"d5","uci":"d7d5","w":0,"d":1,"b":0,"r":2500}],"g":["mc55571","mc97864"]},"rnbqkbnr/pp1p1ppp/2p5/4p3/2P5/1P4P1/P2PPP1P/RNBQKBNR b KQkq -":{"w":3,"d":0,"b":0,"r":2610,"m":[{"san":"d5","uci":"d7d5","w":3,"d":0,"b":0,"r":2610}],"g":["mc55898","mc87318","mc65983"]},"r1bqk2r/ppp1ppbp/2np1np1/8/2PPP3/2NB4/PP2NPPP/R1BQK2R b KQkq -":{"w":1,"d":1,"b":0,"r":2508,"m":[{"san":"e5","uci":"e7e5","w":1,"d":1,"b":0,"r":2508}],"g":["mc56109","mc98398"]},"rn1qk2r/pp2bppp/2p1pnb1/3p4/2PP4/3BPN2/PPQN1PPP/R1B2RK1 b kq -":{"w":0,"d":2,"b":0,"r":2683,"m":[{"san":"Nbd7","uci":"b8d7","w":0,"d":2,"b":0,"r":2683}],"g":["mc57637","mc59368"]},"r1bqkb1r/ppp1pp1p/2np2p1/4P2n/3P4/5N2/PPP1BPPP/RNBQ1RK1 b kq -":{"w":3,"d":0,"b":2,"r":2748,"m":[{"san":"Bg7","uci":"f8g7","w":3,"d":0,"b":2,"r":2748}],"g":["mc61196","mc103688","mc83081","mc82525","mc104823"]},"rn1qkbnr/pp3ppp/2p1p3/3p4/2P3b1/1Q6/PP1PPPBP/RNB1K1NR w KQkq -":{"w":0,"d":0,"b":2,"r":2778,"m":[{"san":"cxd5","uci":"c4d5","w":0,"d":0,"b":2,"r":2778}],"g":["mc62622","mc80292"]},"rnbqk2r/ppp1ppbp/5np1/3p4/1P3P2/4PN2/PBPP2PP/RN1QKB1R b KQkq -":{"w":3,"d":1,"b":2,"r":2533,"m":[{"san":"O-O","uci":"e8g8","w":3,"d":1,"b":2,"r":2533}],"g":["mc63157","mc99193","mc62983","mc63049","mc63090","mc63101"]},"rn1qk2r/ppp1bppp/3p1n2/4p2b/2PP4/2N1PN1P/PP2BPP1/R1BQK2R b KQkq -":{"w":0,"d":2,"b":0,"r":2600,"m":[{"san":"Nbd7","uci":"b8d7","w":0,"d":2,"b":0,"r":2600}],"g":["mc63438","mc99492"]},"rnbqkbnr/ppp1pp1p/3p2p1/8/4PP2/5N2/PPPP2PP/RNBQKB1R b KQkq -":{"w":0,"d":1,"b":1,"r":2646,"m":[{"san":"Bg7","uci":"f8g7","w":0,"d":1,"b":1,"r":2646}],"g":["mc85523","mc64052"]},"rnbq1rk1/ppppbppp/5n2/8/2B1Pp2/2NP4/PPP3PP/R1BQK1NR w KQ -":{"w":1,"d":1,"b":0,"r":2648,"m":[{"san":"Bxf4","uci":"c1f4","w":1,"d":1,"b":0,"r":2648}],"g":["mc80590","mc64664"]},"r1bqk2r/ppp2ppp/2np1n2/2b1p3/4P3/2NP2P1/PPP1NPBP/R1BQK2R b KQkq -":{"w":2,"d":1,"b":0,"r":2653,"m":[{"san":"a6","uci":"a7a6","w":2,"d":1,"b":0,"r":2653}],"g":["mc76237","mc67549","mc64985"]},"r1bqk2r/ppp1bppp/2n5/1B1pN3/3Pn3/8/PPP1QPPP/RNB2RK1 b kq -":{"w":0,"d":1,"b":1,"r":2600,"m":[{"san":"Bd7","uci":"c8d7","w":0,"d":1,"b":1,"r":2600}],"g":["mc65321","mc65561"]},"rn1qkbnr/pp1bpppp/3p4/6B1/3QP3/5N2/PPP2PPP/RN2KB1R b KQkq -":{"w":0,"d":1,"b":1,"r":2545,"m":[{"san":"Nc6","uci":"b8c6","w":0,"d":1,"b":1,"r":2545}],"g":["mc86695","mc66015"]},"r1bqk2r/pp2npbp/2n1p1p1/2pp4/4P3/3P1NP1/PPP1QPBP/RNB1R1K1 b kq -":{"w":0,"d":2,"b":0,"r":2578,"m":[{"san":"b6","uci":"b7b6","w":0,"d":2,"b":0,"r":2578}],"g":["mc66430","mc87785"]},"r2qk1nr/pp3pbp/2p3p1/2p1p3/4P1b1/P2P1N2/1PP2PPP/RNBQR1K1 b kq -":{"w":0,"d":2,"b":0,"r":2703,"m":[{"san":"Nf6","uci":"g8f6","w":0,"d":2,"b":0,"r":2703}],"g":["mc66899","mc93537"]},"r1bqkb1r/1p1n1ppp/p1p1pn2/3p4/2PP4/P1N1PN2/1PQ2PPP/R1B1KB1R b KQkq -":{"w":1,"d":1,"b":0,"r":2738,"m":[{"san":"Qc7","uci":"d8c7","w":1,"d":0,"b":0,"r":2733},{"san":"dxc4","uci":"d5c4","w":0,"d":1,"b":0,"r":2743}],"g":["mc69815","mc69735"]},"rn1qkb1r/pbp2ppp/1p3n2/3pP3/3P4/3B1P2/PP4PP/RNBQK1NR b KQkq -":{"w":0,"d":1,"b":1,"r":2715,"m":[{"san":"Nfd7","uci":"f6d7","w":0,"d":1,"b":1,"r":2715}],"g":["mc69923","mc70022"]},"r1bqkb1r/p2npp1p/2pp1np1/8/1p1PP3/4BP2/PPPQN1PP/2KR1BNR b kq -":{"w":1,"d":0,"b":1,"r":2666,"m":[{"san":"Qa5","uci":"d8a5","w":0,"d":0,"b":1,"r":2650},{"san":"a5","uci":"a7a5","w":1,"d":0,"b":0,"r":2682}],"g":["mc70799","mc70368"]},"r2qkb1r/pp1npppp/2p2n2/3p2Bb/3P4/3BPN1P/PPPN1PP1/R2QK2R b KQkq -":{"w":0,"d":3,"b":0,"r":2703,"m":[{"san":"e6","uci":"e7e6","w":0,"d":3,"b":0,"r":2703}],"g":["mc73916","mc88884","mc90246"]},"rnbqk1nr/pp2ppbp/2p3p1/3p4/8/3P1NP1/PPPNPPBP/R1BQK2R b KQkq -":{"w":2,"d":0,"b":0,"r":2728,"m":[{"san":"a5","uci":"a7a5","w":1,"d":0,"b":0,"r":2775},{"san":"e5","uci":"e7e5","w":1,"d":0,"b":0,"r":2681}],"g":["mc74733","mc75029"]},"rn1qkb1r/pp3ppp/2p1pn2/3p4/3P2b1/1P2PN2/PBPN1PPP/R2QKB1R b KQkq -":{"w":2,"d":0,"b":1,"r":2665,"m":[{"san":"Nbd7","uci":"b8d7","w":1,"d":0,"b":1,"r":2657},{"san":"Be7","uci":"f8e7","w":1,"d":0,"b":0,"r":2681}],"g":["mc75019","mc77592","mc76169"]},"r1bqk1nr/ppp1ppb1/2np2p1/7p/2PPP3/2N1B3/PP2NPPP/R2QKB1R b KQkq -":{"w":0,"d":2,"b":0,"r":2715,"m":[{"san":"e5","uci":"e7e5","w":0,"d":2,"b":0,"r":2715}],"g":["mc77345","mc105143"]},"rnb1kbnr/1p2pppp/1qp5/p2p4/1P1P4/P1P5/1B2PPPP/RN1QKBNR b KQkq -":{"w":2,"d":0,"b":0,"r":2715,"m":[{"san":"Bf5","uci":"c8f5","w":2,"d":0,"b":0,"r":2715}],"g":["mc77355","mc105153"]},"r1bqkbnr/4pppp/p1pp4/8/2PQP3/5N2/PP3PPP/RNB1K2R b KQkq -":{"w":1,"d":0,"b":1,"r":2659,"m":[{"san":"e5","uci":"e7e5","w":1,"d":0,"b":1,"r":2659}],"g":["mc77755","mc99026"]},"rn1qkbnr/pbpp1ppp/4p3/1p6/3PP3/3B1N2/PPP2PPP/RNBQK2R b KQkq -":{"w":1,"d":0,"b":1,"r":2592,"m":[{"san":"c5","uci":"c7c5","w":0,"d":0,"b":1,"r":2605},{"san":"a6","uci":"a7a6","w":1,"d":0,"b":0,"r":2578}],"g":["mc78325","mc100543"]},"r1bqkb1r/ppppnppp/2n5/8/3NP3/2N5/PPP2PPP/R1BQKB1R b KQkq -":{"w":1,"d":0,"b":1,"r":2613,"m":[{"san":"Nxd4","uci":"c6d4","w":1,"d":0,"b":1,"r":2613}],"g":["mc78773","mc102076"]},"rnbqk2r/pp3ppp/2p2n2/2b1p3/4P3/5NP1/PPPN1PBP/R1BQK2R b KQkq -":{"w":2,"d":0,"b":0,"r":2703,"m":[{"san":"Qe7","uci":"d8e7","w":2,"d":0,"b":0,"r":2703}],"g":["mc81267","mc79536"]},"rnbqk2r/1p3ppp/4pn2/2bp4/p1P5/P3PN2/1B1P1PPP/RN1QKB1R b KQkq -":{"w":1,"d":0,"b":2,"r":2687,"m":[{"san":"O-O","uci":"e8g8","w":1,"d":0,"b":1,"r":2702},{"san":"Nc6","uci":"b8c6","w":0,"d":0,"b":1,"r":2657}],"g":["mc79972","mc80760","mc80837"]},"r1bqkb1r/1p1pnppp/p1n1p3/8/4PB2/2N2N2/PP2BPPP/R2QK2R w KQkq -":{"w":2,"d":0,"b":0,"r":2739,"m":[{"san":"Qb3","uci":"d1b3","w":2,"d":0,"b":0,"r":2739}],"g":["mc80162","mc80340"]},"r2qkb1r/pp2pppp/2n2n2/2pp1b2/8/1P1P1NP1/PBPNPP1P/R2QKB1R b KQkq -":{"w":2,"d":0,"b":1,"r":2726,"m":[{"san":"h6","uci":"h7h6","w":1,"d":0,"b":0,"r":2720},{"san":"Qc7","uci":"d8c7","w":1,"d":0,"b":0,"r":2708},{"san":"e6","uci":"e7e6","w":0,"d":0,"b":1,"r":2750}],"g":["mc85307","mc81067","mc81122"]},"r1b1kbnr/pp1npppp/1q6/2ppP3/3P1P2/2P5/PP4PP/RNBQKBNR b KQkq -":{"w":1,"d":0,"b":1,"r":2630,"m":[{"san":"Nh6","uci":"g8h6","w":1,"d":0,"b":1,"r":2630}],"g":["mc82025","mc82027"]},"r1bqkbnr/pp1n1ppp/2p5/4p3/2N5/5NP1/PP1PPPBP/R1BQK2R b KQkq -":{"w":0,"d":2,"b":0,"r":2625,"m":[{"san":"e4","uci":"e5e4","w":0,"d":2,"b":0,"r":2625}],"g":["mc83086","mc95791"]},"rnbqkbnr/pp1ppp1p/6p1/2p5/2PP4/2N5/PP2PPPP/R1BQKBNR b KQkq -":{"w":1,"d":0,"b":1,"r":2734,"m":[{"san":"cxd4","uci":"c5d4","w":1,"d":0,"b":1,"r":2734}],"g":["mc83104","mc110241"]},"rn1q1rk1/ppp1nppp/3b4/3p4/3P1Bb1/3B4/PPP1NPPP/RN1Q1RK1 w - -":{"w":0,"d":2,"b":0,"r":2700,"m":[{"san":"Bxd6","uci":"f4d6","w":0,"d":2,"b":0,"r":2700}],"g":["mc87147","mc99506"]},"rnb1k1nr/p1pq1ppp/1p2p3/3pP3/P2P4/2P5/2P2PPP/R1BQKBNR b KQkq -":{"w":0,"d":2,"b":1,"r":2570,"m":[{"san":"Ba6","uci":"c8a6","w":0,"d":2,"b":1,"r":2570}],"g":["mc87444","mc99786","mc98537"]},"rnbqk2r/pp2ppbp/2p2np1/3p4/2P5/1P3NP1/PBQPPP1P/RN2KB1R b KQkq -":{"w":0,"d":2,"b":0,"r":2583,"m":[{"san":"O-O","uci":"e8g8","w":0,"d":2,"b":0,"r":2583}],"g":["mc106359","mc87786"]},"rnbq1rk1/1p2ppbp/p2p1np1/2pP2B1/2P1P3/2N5/PP1QBPPP/R3K1NR b KQ -":{"w":1,"d":1,"b":0,"r":2588,"m":[{"san":"b5","uci":"b7b5","w":0,"d":1,"b":0,"r":2686},{"san":"e6","uci":"e7e6","w":1,"d":0,"b":0,"r":2490}],"g":["mc88471","mc91662"]},"rnbqkbnr/1p3ppp/p7/2pp4/3P4/2P1BN2/PP3PPP/RN1QKB1R b KQkq -":{"w":0,"d":1,"b":1,"r":2731,"m":[{"san":"c4","uci":"c5c4","w":0,"d":1,"b":1,"r":2731}],"g":["mc103611","mc88550"]},"r3k1nr/pbppqppp/1pn1p3/2b5/4P3/1PN5/PBPPQPPP/1K1R1BNR b kq -":{"w":2,"d":0,"b":0,"r":2740,"m":[{"san":"Nf6","uci":"g8f6","w":2,"d":0,"b":0,"r":2740}],"g":["mc89862","mc105018"]},"rnbq1rk1/pp3ppp/4pn2/2bp4/5B2/3BPN2/PPPN1PPP/R2QK2R b KQ -":{"w":0,"d":2,"b":0,"r":2592,"m":[{"san":"Nc6","uci":"b8c6","w":0,"d":2,"b":0,"r":2592}],"g":["mc90407","mc90380"]},"rn1qk2r/pp1bnppp/4p3/2ppP3/3P4/P1PB1N2/2P2PPP/R1BQK2R b KQkq -":{"w":2,"d":1,"b":0,"r":2603,"m":[{"san":"c4","uci":"c5c4","w":2,"d":1,"b":0,"r":2603}],"g":["mc108114","mc108011","mc97842"]},"r1bqk2r/ppp3bp/2np1np1/4pp2/2P5/2NPP1P1/PP3PBP/1RBQK1NR w Kkq -":{"w":0,"d":1,"b":1,"r":2563,"m":[{"san":"Nge2","uci":"g1e2","w":0,"d":1,"b":1,"r":2563}],"g":["mc107990","mc101504"]}}